{"data": [{"id": 30204, "type": "episode", "attributes": {"title": "Black Ops 4 - Whiteout", "slug": "things-to-do-in-2019-blackout-whiteout", "rating": null, "caption": "When snow falls on Black Ops 4 Blackout, the guys decide to take a break from bleeding out from bullets. Their new favorite pastime is bleeding out from snowballs.", "number": 1, "description": "When snow falls on Black Ops 4 Blackout, the guys decide to take a break from bleeding out from bullets. Their new favorite pastime is bleeding out from snowballs.", "display_title": "Black Ops 4 - Whiteout", "length": 617, "advert_config": "", "advertising": true, "ad_timestamps": "308.00", "public_golive_at": "2019-01-17T18:00:00.000Z", "sponsor_golive_at": "2019-01-16T18:00:00.000Z", "member_golive_at": "2019-01-17T18:00:00.000Z", "original_air_date": "2019-01-16T18:00:00.000Z", "channel_id": "2cb2a70c-be50-46f5-93d7-84a1baabb4f7", "channel_slug": "achievement-hunter", "season_id": "2f82d4de-1559-4f07-8012-66dfd44aa26b", "season_slug": "things-to-do-in-2019", "season_number": 9, "show_title": "Things to Do In", "show_id": "ff9288dd-464d-11e7-a302-065410f210c4", "show_slug": "things-to-do-in", "is_sponsors_only": false, "member_tier_i": -1, "sort_number": 90001, "genres": [], "is_live": true, "is_schedulable": true, "season_order": "desc", "episode_order": "desc", "downloadable": true, "blacklisted_countries": [], "upsell_next": false, "trending_score": 1.0, "time_boost": 19.011618, "credits_start_at": null, "trending_carousel": null}, "uuid": "4042cb9e-4ef4-400e-869e-d2b959d53750", "canonical_links": {"self": "/watch/things-to-do-in-2019-blackout-whiteout", "show": "/series/things-to-do-in"}, "archive": {"id": "roosterteeth-30204", "status": "archived", "files": [{"name": "2019-01-16_Black_Ops_4_-_Whiteout_[30204].description", "filesize": 163, "file_ext": "description", "md5": "084f16b443b7a0a67dc19cdd52681a46"}, {"name": "2019-01-16_Black_Ops_4_-_Whiteout_[30204].info.json", "filesize": 19656, "file_ext": "json", "md5": "638b0bf22f34017e0051e7c189960e39"}, {"name": "2019-01-16_Black_Ops_4_-_Whiteout_[30204].jpg", "filesize": 186980, "file_ext": "jpg", "md5": "3aff4fa1d26d2daa5e67e35452e37afb"}, {"name": "2019-01-16_Black_Ops_4_-_Whiteout_[30204].mp4", "filesize": 321040964, "file_ext": "mp4", "md5": "a5814c3bc9e1b1434f1a5004042198b1"}]}}, {"id": 30473, "type": "episode", "attributes": {"title": "RED DEAD VALENTINE - Red Dead Redemption 2: Online", "slug": "things-to-do-in-2019-valentines", "rating": null, "caption": "We wanted to share our love with you by making an old-time Valentine's Day postcard in Red Dead Redemption 2: Online.", "number": 2, "description": "We wanted to share our love with you by making an old-time Valentine's Day postcard in Red Dead Redemption 2: Online.", "display_title": "RED DEAD VALENTINE - Red Dead Redemption 2: Online", "length": 895, "advert_config": "", "advertising": true, "ad_timestamps": "284.00,572.00", "public_golive_at": "2019-02-14T18:00:00.000Z", "sponsor_golive_at": "2019-02-13T18:00:00.000Z", "member_golive_at": "2019-02-14T18:00:00.000Z", "original_air_date": "2019-02-13T18:00:00.000Z", "channel_id": "2cb2a70c-be50-46f5-93d7-84a1baabb4f7", "channel_slug": "achievement-hunter", "season_id": "2f82d4de-1559-4f07-8012-66dfd44aa26b", "season_slug": "things-to-do-in-2019", "season_number": 9, "show_title": "Things to Do In", "show_id": "ff9288dd-464d-11e7-a302-065410f210c4", "show_slug": "things-to-do-in", "is_sponsors_only": false, "member_tier_i": -1, "sort_number": 90002, "genres": [], "is_live": true, "is_schedulable": true, "season_order": "desc", "episode_order": "desc", "downloadable": true, "blacklisted_countries": [], "upsell_next": false, "trending_score": 1.0, "time_boost": 19.021318, "credits_start_at": null, "trending_carousel": null}, "uuid": "26dadc9a-df0e-4204-a8b6-0989bd422613", "canonical_links": {"self": "/watch/things-to-do-in-2019-valentines", "show": "/series/things-to-do-in"}, "archive": {"id": "roosterteeth-30473", "status": "archived", "files": [{"name": "2019-02-13_RED_DEAD_VALENTINE_-_Red_Dead_Redemption_2_Online_[30473].description", "filesize": 117, "file_ext": "description", "md5": "b5d525b64eeb34e77eecc7433d66300c"}, {"name": "2019-02-13_RED_DEAD_VALENTINE_-_Red_Dead_Redemption_2_Online_[30473].info.json", "filesize": 19678, "file_ext": "json", "md5": "7d535eec599c03c7e990fa0694104c85"}, {"name": "2019-02-13_RED_DEAD_VALENTINE_-_Red_Dead_Redemption_2_Online_[30473].jpg", "filesize": 330438, "file_ext": "jpg", "md5": "8fea7f5ddf17746b3acaa8a139ffcc48"}, {"name": "2019-02-13_RED_DEAD_VALENTINE_-_Red_Dead_Redemption_2_Online_[30473].mp4", "filesize": 459095326, "file_ext": "mp4", "md5": "fc455362ec54d139483c476f0fa0d61a"}]}}, {"id": 31530, "type": "episode", "attributes": {"title": "NESSY EASTER EGG - Apex Legends", "slug": "things-to-do-in-2019-nessy-easter-egg-apex-legends", "rating": null, "caption": "Geoff, Ryan, and Matt squad up in Apex Legends to try and uncover the mystery of the illusive Lochness Monster.", "number": 3, "description": "Geoff, Ryan, and Matt squad up in Apex Legends to try and uncover the mystery of the illusive Lochness Monster.", "display_title": "NESSY EASTER EGG - Apex Legends", "length": 674, "advert_config": "", "advertising": true, "ad_timestamps": "337.00", "public_golive_at": "2019-02-21T18:00:00.000Z", "sponsor_golive_at": "2019-02-20T18:00:00.000Z", "member_golive_at": "2019-02-21T18:00:00.000Z", "original_air_date": "2019-02-20T18:00:00.000Z", "channel_id": "2cb2a70c-be50-46f5-93d7-84a1baabb4f7", "channel_slug": "achievement-hunter", "season_id": "2f82d4de-1559-4f07-8012-66dfd44aa26b", "season_slug": "things-to-do-in-2019", "season_number": 9, "show_title": "Things to Do In", "show_id": "ff9288dd-464d-11e7-a302-065410f210c4", "show_slug": "things-to-do-in", "is_sponsors_only": false, "member_tier_i": -1, "sort_number": 90003, "genres": [], "is_live": true, "is_schedulable": true, "season_order": "desc", "episode_order": "desc", "downloadable": true, "blacklisted_countries": [], "upsell_next": false, "trending_score": 1.0, "time_boost": 19.022018, "credits_start_at": null, "trending_carousel": null}, "uuid": "8dad137a-8232-46f5-bcef-ee8707437898", "canonical_links": {"self": "/watch/things-to-do-in-2019-nessy-easter-egg-apex-legends", "show": "/series/things-to-do-in"}, "archive": {"id": "roosterteeth-31530", "status": "archived", "files": [{"name": "2019-02-20_NESSY_EASTER_EGG_-_Apex_Legends_[31530].description", "filesize": 111, "file_ext": "description", "md5": "408fa998adfdf9289772f976e83c1d8c"}, {"name": "2019-02-20_NESSY_EASTER_EGG_-_Apex_Legends_[31530].info.json", "filesize": 19672, "file_ext": "json", "md5": "f75915891a634e410b37cc6f64d858f6"}, {"name": "2019-02-20_NESSY_EASTER_EGG_-_Apex_Legends_[31530].jpg", "filesize": 270565, "file_ext": "jpg", "md5": "5fb3394e4fd203be4dce7c5a5260c8c0"}, {"name": "2019-02-20_NESSY_EASTER_EGG_-_Apex_Legends_[31530].mp4", "filesize": 341819088, "file_ext": "mp4", "md5": "d6688f692c4c19f02f3744431f2043cd"}]}}, {"id": 31711, "type": "episode", "attributes": {"title": "Crackdown 3 - Tether Tantrum", "slug": "things-to-do-in-2019-crackdown", "rating": null, "caption": "Matt discovers that playing with tethers in Crackdown 3 can cause massive destruction to the game's physics engine.", "number": 4, "description": "Matt discovers that playing with tethers in Crackdown 3 can cause massive destruction to the game's physics engine.", "display_title": "Crackdown 3 - Tether Tantrum", "length": 270, "advert_config": "", "advertising": true, "ad_timestamps": "270", "public_golive_at": "2019-03-07T18:00:00.000Z", "sponsor_golive_at": "2019-03-06T18:00:00.000Z", "member_golive_at": "2019-03-07T18:00:00.000Z", "original_air_date": "2019-03-06T18:00:00.000Z", "channel_id": "2cb2a70c-be50-46f5-93d7-84a1baabb4f7", "channel_slug": "achievement-hunter", "season_id": "2f82d4de-1559-4f07-8012-66dfd44aa26b", "season_slug": "things-to-do-in-2019", "season_number": 9, "show_title": "Things to Do In", "show_id": "ff9288dd-464d-11e7-a302-065410f210c4", "show_slug": "things-to-do-in", "is_sponsors_only": false, "member_tier_i": -1, "sort_number": 90004, "genres": [], "is_live": true, "is_schedulable": true, "season_order": "desc", "episode_order": "desc", "downloadable": true, "blacklisted_countries": [], "upsell_next": false, "trending_score": 1.0, "time_boost": 19.030618, "credits_start_at": null, "trending_carousel": null}, "uuid": "1faf3c65-702e-4f21-9a3d-58f075a7b61f", "canonical_links": {"self": "/watch/things-to-do-in-2019-crackdown", "show": "/series/things-to-do-in"}, "archive": {"id": "roosterteeth-31711", "status": "archived", "files": [{"name": "2019-03-06_Crackdown_3_-_Tether_Tantrum_[31711].description", "filesize": 115, "file_ext": "description", "md5": "68d54efee10ebee14afe81aa2f223b8b"}, {"name": "2019-03-06_Crackdown_3_-_Tether_Tantrum_[31711].info.json", "filesize": 19617, "file_ext": "json", "md5": "aa15a0933d76f4feca6c86cbb3813877"}, {"name": "2019-03-06_Crackdown_3_-_Tether_Tantrum_[31711].mp4", "filesize": 142992976, "file_ext": "mp4", "md5": "b8e1c089d9d94228432307bd51912836"}, {"name": "2019-03-06_Crackdown_3_-_Tether_Tantrum_[31711].png", "filesize": 258057, "file_ext": "png", "md5": "6de0d9b14d9e01368e27e287323fdd47"}]}}, {"id": 34492, "type": "episode", "attributes": {"title": "Longest Gunpowder Barrel Chain! - Sea of Thieves", "slug": "things-to-do-in-2019-sea-of-thieves-8-13", "rating": null, "caption": "Sea of Thieves has made getting gunpowder barrels easier than ever in it's newest update. Let's try and do some crazy stuff with them!", "number": 5, "description": "Sea of Thieves has made getting gunpowder barrels easier than ever in it's newest update. Let's try and do some crazy stuff with them!", "display_title": "Longest Gunpowder Barrel Chain! - Sea of Thieves", "length": 266, "advert_config": "", "advertising": true, "ad_timestamps": "266", "public_golive_at": "2019-08-13T17:00:00.000Z", "sponsor_golive_at": "2019-08-13T17:00:00.000Z", "member_golive_at": "2019-08-13T17:00:00.000Z", "original_air_date": "2019-08-13T17:00:00.000Z", "channel_id": "2cb2a70c-be50-46f5-93d7-84a1baabb4f7", "channel_slug": "achievement-hunter", "season_id": "2f82d4de-1559-4f07-8012-66dfd44aa26b", "season_slug": "things-to-do-in-2019", "season_number": 9, "show_title": "Things to Do In", "show_id": "ff9288dd-464d-11e7-a302-065410f210c4", "show_slug": "things-to-do-in", "is_sponsors_only": false, "member_tier_i": -1, "sort_number": 90005, "genres": [], "is_live": true, "is_schedulable": true, "season_order": "desc", "episode_order": "desc", "downloadable": true, "blacklisted_countries": [], "upsell_next": false, "trending_score": 1.0, "time_boost": 19.081317, "credits_start_at": null, "trending_carousel": null}, "uuid": "735fe4be-0768-4791-ac24-722db895e60b", "canonical_links": {"self": "/watch/things-to-do-in-2019-sea-of-thieves-8-13", "show": "/series/things-to-do-in"}, "archive": {"id": "roosterteeth-34492", "status": "archived", "files": [{"name": "2019-08-13_Longest_Gunpowder_Barrel_Chain_-_Sea_of_Thieves_[34492].description", "filesize": 134, "file_ext": "description", "md5": "2148e2a26b79b7ef5a6dd7e62c2b8311"}, {"name": "2019-08-13_Longest_Gunpowder_Barrel_Chain_-_Sea_of_Thieves_[34492].info.json", "filesize": 19715, "file_ext": "json", "md5": "23f5d4d17e4cc9f2c3c99be0ba82f34f"}, {"name": "2019-08-13_Longest_Gunpowder_Barrel_Chain_-_Sea_of_Thieves_[34492].jpg", "filesize": 266638, "file_ext": "jpg", "md5": "e3013e8d4c4dc6475522c6ff728e008e"}, {"name": "2019-08-13_Longest_Gunpowder_Barrel_Chain_-_Sea_of_Thieves_[34492].mp4", "filesize": 138665150, "file_ext": "mp4", "md5": "e5f2f6c2c33f5e97c9ac68f01a9b55bd"}]}}, {"id": 34562, "type": "episode", "attributes": {"title": "Chaining Gunpowder Between Two Islands - Sea of Thieves", "slug": "things-to-do-in-2019-sea-of-thieves-8-17", "rating": null, "caption": "We make a 200+ gunpowder barrel explosion between two islands.", "number": 6, "description": "We make a 200+ gunpowder barrel explosion between two islands.\r\nOur last gunpowder barrel chains were insane, but we wanted to go bigger. Now we're chaining over 200 barrel explosions between two islands. Our Sea of Thieves gameplay has never looked this majestic.", "display_title": "Chaining Gunpowder Between Two Islands - Sea of Thieves", "length": 225, "advert_config": "", "advertising": true, "ad_timestamps": "225", "public_golive_at": "2019-08-17T17:00:00.000Z", "sponsor_golive_at": "2019-08-17T17:00:00.000Z", "member_golive_at": "2019-08-17T17:00:00.000Z", "original_air_date": "2019-08-17T17:00:00.000Z", "channel_id": "2cb2a70c-be50-46f5-93d7-84a1baabb4f7", "channel_slug": "achievement-hunter", "season_id": "2f82d4de-1559-4f07-8012-66dfd44aa26b", "season_slug": "things-to-do-in-2019", "season_number": 9, "show_title": "Things to Do In", "show_id": "ff9288dd-464d-11e7-a302-065410f210c4", "show_slug": "things-to-do-in", "is_sponsors_only": false, "member_tier_i": -1, "sort_number": 90006, "genres": [], "is_live": true, "is_schedulable": true, "season_order": "desc", "episode_order": "desc", "downloadable": true, "blacklisted_countries": [], "upsell_next": false, "trending_score": 1.0, "time_boost": 19.081717, "credits_start_at": null, "trending_carousel": null}, "uuid": "784b5f03-b3b4-4f90-bb82-b72526428199", "canonical_links": {"self": "/watch/things-to-do-in-2019-sea-of-thieves-8-17", "show": "/series/things-to-do-in"}, "archive": {"id": "roosterteeth-34562", "status": "archived", "files": [{"name": "2019-08-17_Chaining_Gunpowder_Between_Two_Islands_-_Sea_of_Thieves_[34562].description", "filesize": 264, "file_ext": "description", "md5": "6a974c2e0a91c32781d302622b01ceea"}, {"name": "2019-08-17_Chaining_Gunpowder_Between_Two_Islands_-_Sea_of_Thieves_[34562].info.json", "filesize": 19868, "file_ext": "json", "md5": "81c68e7d4310b4e661d26bc84c648db2"}, {"name": "2019-08-17_Chaining_Gunpowder_Between_Two_Islands_-_Sea_of_Thieves_[34562].jpg", "filesize": 221294, "file_ext": "jpg", "md5": "dde84a1956d0e5352705d2ae836cba95"}, {"name": "2019-08-17_Chaining_Gunpowder_Between_Two_Islands_-_Sea_of_Thieves_[34562].mp4", "filesize": 118497120, "file_ext": "mp4", "md5": "5770ee82f1957c9efef87d165764c778"}]}}, {"id": 35575, "type": "episode", "attributes": {"title": "Can You Survive the Garden of Salvation at 100 Light?", "slug": "things-to-do-in-2019-can-you-survive-the-garden-of-salvation-at-100-light", "rating": null, "caption": "Destiny's raids have always been a massive challenge even when you're at max level. How hard must they be when you're as far from max as possible?", "number": 7, "description": "Destiny's raids have always been a massive challenge even when you're at max level. How hard must they be when you're as far from max as possible?", "display_title": "Can You Survive the Garden of Salvation at 100 Light?", "length": 469, "advert_config": "", "advertising": true, "ad_timestamps": "234.00", "public_golive_at": "2019-11-02T17:00:00.000Z", "sponsor_golive_at": "2019-11-01T17:00:00.000Z", "member_golive_at": "2019-11-02T17:00:00.000Z", "original_air_date": "2019-11-01T17:00:00.000Z", "channel_id": "2cb2a70c-be50-46f5-93d7-84a1baabb4f7", "channel_slug": "achievement-hunter", "season_id": "2f82d4de-1559-4f07-8012-66dfd44aa26b", "season_slug": "things-to-do-in-2019", "season_number": 9, "show_title": "Things to Do In", "show_id": "ff9288dd-464d-11e7-a302-065410f210c4", "show_slug": "things-to-do-in", "is_sponsors_only": false, "member_tier_i": -1, "sort_number": 90007, "genres": [], "is_live": true, "is_schedulable": true, "season_order": "desc", "episode_order": "desc", "downloadable": true, "blacklisted_countries": [], "upsell_next": false, "trending_score": 1.0, "time_boost": 19.110117, "credits_start_at": null, "trending_carousel": null}, "uuid": "3d45d31b-0253-41ff-a983-b298b31e2f5f", "canonical_links": {"self": "/watch/things-to-do-in-2019-can-you-survive-the-garden-of-salvation-at-100-light", "show": "/series/things-to-do-in"}, "archive": {"id": "roosterteeth-35575", "status": "archived", "files": [{"name": "2019-11-01_Can_You_Survive_the_Garden_of_Salvation_at_100_Light_[35575].description", "filesize": 146, "file_ext": "description", "md5": "e3a90188c83f0b838b01b9bb8cf31a9c"}, {"name": "2019-11-01_Can_You_Survive_the_Garden_of_Salvation_at_100_Light_[35575].info.json", "filesize": 19852, "file_ext": "json", "md5": "0b8e7a1b11bc8261f25be167f956305a"}, {"name": "2019-11-01_Can_You_Survive_the_Garden_of_Salvation_at_100_Light_[35575].jpg", "filesize": 403947, "file_ext": "jpg", "md5": "64b192fe40d98996f0eb15a0e86e2af3"}, {"name": "2019-11-01_Can_You_Survive_the_Garden_of_Salvation_at_100_Light_[35575].mp4", "filesize": 242664202, "file_ext": "mp4", "md5": "be659c7b457569f5d002ab3c03e678db"}]}}, {"id": 35913, "type": "episode", "attributes": {"title": "Can the President Cause a Voidout? - Death Stranding", "slug": "things-to-do-can-the-president-cause-a-voidout-death-stranding", "rating": null, "caption": "What happens if you wait the 48 hours it takes for a dead body to explode in Death Stranding? And what if that dead body was also your mom's?", "number": 249, "description": "What happens if you wait the 48 hours it takes for a dead body to explode in Death Stranding? And what if that dead body was also your mom's?", "display_title": "Can the President Cause a Voidout? - Death Stranding", "length": 297, "advert_config": "", "advertising": true, "ad_timestamps": "297", "public_golive_at": "2019-11-27T20:00:00.000Z", "sponsor_golive_at": "2019-11-27T20:00:00.000Z", "member_golive_at": "2019-11-27T20:00:00.000Z", "original_air_date": "2019-11-27T20:00:00.000Z", "channel_id": "2cb2a70c-be50-46f5-93d7-84a1baabb4f7", "channel_slug": "achievement-hunter", "season_id": "2f82d4de-1559-4f07-8012-66dfd44aa26b", "season_slug": "things-to-do-in-2019", "season_number": 9, "show_title": "Things to Do In", "show_id": "ff9288dd-464d-11e7-a302-065410f210c4", "show_slug": "things-to-do-in", "is_sponsors_only": false, "member_tier_i": -1, "sort_number": 90249, "genres": [], "is_live": true, "is_schedulable": true, "season_order": "desc", "episode_order": "desc", "downloadable": true, "blacklisted_countries": [], "upsell_next": false, "trending_score": 1.0, "time_boost": 19.11272, "credits_start_at": null, "trending_carousel": null}, "uuid": "ff995820-2dbc-4efd-a75e-d6fce1b76809", "canonical_links": {"self": "/watch/things-to-do-can-the-president-cause-a-voidout-death-stranding", "show": "/series/things-to-do-in"}, "archive": {"id": "roosterteeth-35913", "status": "archived", "files": [{"name": "2019-11-27_Can_the_President_Cause_a_Voidout_-_Death_Stranding_[35913].description", "filesize": 141, "file_ext": "description", "md5": "0ddf76c25a67d1c71a0414b7be49eb2b"}, {"name": "2019-11-27_Can_the_President_Cause_a_Voidout_-_Death_Stranding_[35913].info.json", "filesize": 19802, "file_ext": "json", "md5": "c7b7f6ca306c55119bb1f80fd86dc709"}, {"name": "2019-11-27_Can_the_President_Cause_a_Voidout_-_Death_Stranding_[35913].jpg", "filesize": 296442, "file_ext": "jpg", "md5": "077e3706a736ed7b16ae094eb69cdcc7"}, {"name": "2019-11-27_Can_the_President_Cause_a_Voidout_-_Death_Stranding_[35913].mp4", "filesize": 157428050, "file_ext": "mp4", "md5": "9b6f5dc7fd631e8cd677df1bcf0cc795"}]}}], "page": 1, "per_page": 999, "total_pages": 1, "total_results": 8}