{"data":[{"id":1750,"type":"episode","attributes":{"title":"Resident Evil 7 - Episode 0","slug":"backwardz-compatible-2017-resident-evil-7-episode-0","number":1,"description":"We're back and with a brand new game that's not out yet so that's why we are playing the demo! Watch Miles lose his shit as Kyle guides him through a dilapidated old house while being stalked by a homicidal old man. Unfortunately that's not the only horror this house contains. It's Backwardz Compatible and we are playing Resident Evil 7!","length":5352,"original_air_date":"2017-01-20T23:00:00.000Z","channel_id":"92b6bb21-91d2-4b1b-bf95-3268fa0d9939","channel_slug":"rooster-teeth","season_id":"ffa323b7-464d-11e7-a302-065410f210c4","season_slug":"backwardz-compatible-2017","season_number":4,"show_title":"Backwardz Compatible","show_id":"ff93ec57-464d-11e7-a302-065410f210c4","show_slug":"backwardz-compatible","is_sponsors_only":true},"uuid":"00527bab-464e-11e7-a302-065410f210c4","archive":{"id":"roosterteeth-1750","status":"archived","files":[{"name":"2017-01-20_Resident_Evil_7_-_Episode_0_[1750].description","filesize":339,"file_ext":"description","md5":"594d55ec0c66863be33ec81277b4e132"},{"name":"2017-01-20_Resident_Evil_7_-_Episode_0_[1750].info.json","filesize":20137,"file_ext":"json","md5":"03ce0cdbb1c69c3cfccbb3646a84b174"},{"name":"2017-01-20_Resident_Evil_7_-_Episode_0_[1750].mp4","filesize":2807486816,"file_ext":"mp4","md5":"88cc9784bc1da22bdba225b894034f30"},{"name":"2017-01-20_Resident_Evil_7_-_Episode_0_[1750].png","filesize":241593,"file_ext":"png","md5":"751cb00d30f9446a03630d7b6ae63f8b"}]}},{"id":1748,"type":"episode","attributes":{"title":"RE7 #1 - Welcome to the Family","slug":"backwardz-compatible-2017-re7-1-welcome-to-the-family","number":2,"description":"Resident Evil 7 is finally out! Kyle and Miles are in a search for Ethan's missing wife. Along the way they break into private property, watch someone else's home movies, order a pizza, and do everything wrong while trying to solve a domestic dispute.","length":3190,"original_air_date":"2017-01-27T21:00:00.000Z","channel_id":"92b6bb21-91d2-4b1b-bf95-3268fa0d9939","channel_slug":"rooster-teeth","season_id":"ffa323b7-464d-11e7-a302-065410f210c4","season_slug":"backwardz-compatible-2017","season_number":4,"show_title":"Backwardz Compatible","show_id":"ff93ec57-464d-11e7-a302-065410f210c4","show_slug":"backwardz-compatible","is_sponsors_only":true},"uuid":"0052eb2c-464e-11e7-a302-065410f210c4","archive":{"id":"roosterteeth-1748","status":"archived","files":[{"name":"2017-01-27_RE7_1_-_Welcome_to_the_Family_[1748].description","filesize":251,"file_ext":"description","md5":"efb60ed047d59ea3862f1a5aa6424193"},{"name":"2017-01-27_RE7_1_-_Welcome_to_the_Family_[1748].info.json","filesize":20062,"file_ext":"json","md5":"3090caee5ef878744bde3591aef65ad3"},{"name":"2017-01-27_RE7_1_-_Welcome_to_the_Family_[1748].mp4","filesize":1655117354,"file_ext":"mp4","md5":"0b50793c6292b2110793e788b4f74922"},{"name":"2017-01-27_RE7_1_-_Welcome_to_the_Family_[1748].png","filesize":240672,"file_ext":"png","md5":"94715aff8523a1edc37a2e2d6a6f17a2"}]}},{"id":1747,"type":"episode","attributes":{"title":"RE7 #2 - Daddy Ain't Happy","slug":"backwardz-compatible-2017-re7-2","number":3,"description":"Kyle and Miles sit down to a nice, quiet, cannibalistic family dinner but when they try to leave early without helping with the dishes well... Daddy gets a little pissed off.","length":3673,"original_air_date":"2017-02-03T21:00:00.000Z","channel_id":"92b6bb21-91d2-4b1b-bf95-3268fa0d9939","channel_slug":"rooster-teeth","season_id":"ffa323b7-464d-11e7-a302-065410f210c4","season_slug":"backwardz-compatible-2017","season_number":4,"show_title":"Backwardz Compatible","show_id":"ff93ec57-464d-11e7-a302-065410f210c4","show_slug":"backwardz-compatible","is_sponsors_only":true},"uuid":"0053e124-464e-11e7-a302-065410f210c4","archive":{"id":"roosterteeth-1747","status":"archived","files":[{"name":"2017-02-03_RE7_2_-_Daddy_Aint_Happy_[1747].description","filesize":174,"file_ext":"description","md5":"e0f976a164376ee84a4c171d0a06c944"},{"name":"2017-02-03_RE7_2_-_Daddy_Aint_Happy_[1747].info.json","filesize":19909,"file_ext":"json","md5":"2c367c2b86d0a1daec03998426bc8fea"},{"name":"2017-02-03_RE7_2_-_Daddy_Aint_Happy_[1747].mp4","filesize":1919066069,"file_ext":"mp4","md5":"7ae00e509814e8c7f5679f0e2adaff6b"},{"name":"2017-02-03_RE7_2_-_Daddy_Aint_Happy_[1747].png","filesize":241606,"file_ext":"png","md5":"7007e9f0351e5ec1eec3a7bd02d64ed7"}]}},{"id":1746,"type":"episode","attributes":{"title":"RE7 #3 - Poor Deputy","slug":"backwardz-compatible-2017-re7-3","number":4,"description":"Kyle and Miles head into the basement and meet up with their old friend Larry...and his friend...and his several other friends. It's ok though because Larry got Kyle and Miles front row tickets to a steel cage match. He just forgot to tell them that the front row is in the cage.","length":3238,"original_air_date":"2017-02-10T21:00:00.000Z","channel_id":"92b6bb21-91d2-4b1b-bf95-3268fa0d9939","channel_slug":"rooster-teeth","season_id":"ffa323b7-464d-11e7-a302-065410f210c4","season_slug":"backwardz-compatible-2017","season_number":4,"show_title":"Backwardz Compatible","show_id":"ff93ec57-464d-11e7-a302-065410f210c4","show_slug":"backwardz-compatible","is_sponsors_only":true},"uuid":"005464e6-464e-11e7-a302-065410f210c4","archive":{"id":"roosterteeth-1746","status":"archived","files":[{"name":"2017-02-10_RE7_3_-_Poor_Deputy_[1746].description","filesize":279,"file_ext":"description","md5":"ab4ea05acbd651e0b116d8f62851d305"},{"name":"2017-02-10_RE7_3_-_Poor_Deputy_[1746].info.json","filesize":19994,"file_ext":"json","md5":"5650b3c10d0394624165da81952bb405"},{"name":"2017-02-10_RE7_3_-_Poor_Deputy_[1746].mp4","filesize":1697386151,"file_ext":"mp4","md5":"b37147d777a8cc59692252a90711f692"},{"name":"2017-02-10_RE7_3_-_Poor_Deputy_[1746].png","filesize":241553,"file_ext":"png","md5":"e02fcf662632f3682b08a97d6f79f5ed"}]}},{"id":1745,"type":"episode","attributes":{"title":"RE7 #4 - Mama's Babies","slug":"backwardz-compatible-2017-re7-4","number":5,"description":"Gray Haddock joins Kyle and Miles as they try to fumigate the old house of Marguerite's \"babies\". Things go sideways almost immediately when the guys realize they just brought a knife to a wasp fight. However with some red neck engineering and a page ripped from Ellen Ripley's Big Book of Bug Extermination Techniques, the gang find a way to even the playing field.","length":3481,"original_air_date":"2017-02-17T21:00:00.000Z","channel_id":"92b6bb21-91d2-4b1b-bf95-3268fa0d9939","channel_slug":"rooster-teeth","season_id":"ffa323b7-464d-11e7-a302-065410f210c4","season_slug":"backwardz-compatible-2017","season_number":4,"show_title":"Backwardz Compatible","show_id":"ff93ec57-464d-11e7-a302-065410f210c4","show_slug":"backwardz-compatible","is_sponsors_only":true},"uuid":"0054f6fa-464e-11e7-a302-065410f210c4","archive":{"id":"roosterteeth-1745","status":"archived","files":[{"name":"2017-02-17_RE7_4_-_Mamas_Babies_[1745].description","filesize":366,"file_ext":"description","md5":"975c61e6b66e3fb1cd7458914278f995"},{"name":"2017-02-17_RE7_4_-_Mamas_Babies_[1745].info.json","filesize":20100,"file_ext":"json","md5":"4cc7b4c99663014f486ea16e794763f8"},{"name":"2017-02-17_RE7_4_-_Mamas_Babies_[1745].mp4","filesize":1820201476,"file_ext":"mp4","md5":"b16decc662e05bf4b14be76acdcf8c81"},{"name":"2017-02-17_RE7_4_-_Mamas_Babies_[1745].png","filesize":243667,"file_ext":"png","md5":"0f1db3f9704f3ba31946fbdd752ca093"}]}},{"id":1743,"type":"episode","attributes":{"title":"RE7 #6 - Happy Birthday!","slug":"backwardz-compatible-2017-re7-6-happy-birthday","number":7,"description":"Kyle and Miles have cut down Jack and killed Marguerite so now it's Lucas' turn. Before that can happen the duo must find two key cards, navigate a house full of new booby traps and watch dear old Clancy struggle with one of Lucas' more sinister puzzles. (Miles would just like to point out that HE was the one who killed Jack and Marguerite, not Kyle)","length":4034,"original_air_date":"2017-03-04T21:00:00.000Z","channel_id":"92b6bb21-91d2-4b1b-bf95-3268fa0d9939","channel_slug":"rooster-teeth","season_id":"ffa323b7-464d-11e7-a302-065410f210c4","season_slug":"backwardz-compatible-2017","season_number":4,"show_title":"Backwardz Compatible","show_id":"ff93ec57-464d-11e7-a302-065410f210c4","show_slug":"backwardz-compatible","is_sponsors_only":true},"uuid":"00567cd0-464e-11e7-a302-065410f210c4","archive":{"id":"roosterteeth-1743","status":"archived","files":[{"name":"2017-03-04_RE7_6_-_Happy_Birthday_[1743].description","filesize":352,"file_ext":"description","md5":"a5cd4160c86015739dd8003d7f82dc20"},{"name":"2017-03-04_RE7_6_-_Happy_Birthday_[1743].info.json","filesize":20126,"file_ext":"json","md5":"e6e5ae0e31586fcef4352b23cf1f4984"},{"name":"2017-03-04_RE7_6_-_Happy_Birthday_[1743].mp4","filesize":2111408755,"file_ext":"mp4","md5":"33bef2de9fe2e89258b50da137f54f8d"},{"name":"2017-03-04_RE7_6_-_Happy_Birthday_[1743].png","filesize":241484,"file_ext":"png","md5":"7ab0b20bf2c27c396d6cef0e3c6ed5c0"}]}},{"id":1742,"type":"episode","attributes":{"title":"RE7 #7 - Brawl in the Bayou","slug":"backwardz-compatible-2017-re7-7","number":8,"description":"Kyle and Miles find themselves stuck in Lucas' puzzle room but this time as Ethan. Luckily the duo have read Clancy's Pro Strategy Guide and know all the tips and tricks to help get them out. However the prize for solving this puzzle might not be something they want; the return of an old friend who's lookin' for a rematch.","length":3368,"original_air_date":"2017-03-10T21:00:00.000Z","channel_id":"92b6bb21-91d2-4b1b-bf95-3268fa0d9939","channel_slug":"rooster-teeth","season_id":"ffa323b7-464d-11e7-a302-065410f210c4","season_slug":"backwardz-compatible-2017","season_number":4,"show_title":"Backwardz Compatible","show_id":"ff93ec57-464d-11e7-a302-065410f210c4","show_slug":"backwardz-compatible","is_sponsors_only":true},"uuid":"0056f3c1-464e-11e7-a302-065410f210c4","archive":{"id":"roosterteeth-1742","status":"archived","files":[{"name":"2017-03-10_RE7_7_-_Brawl_in_the_Bayou_[1742].description","filesize":324,"file_ext":"description","md5":"3ac5840b84a92b9f36e074e4240c6f47"},{"name":"2017-03-10_RE7_7_-_Brawl_in_the_Bayou_[1742].info.json","filesize":20049,"file_ext":"json","md5":"4fab6aec8b4ea5042fb0cc852dcd3ab3"},{"name":"2017-03-10_RE7_7_-_Brawl_in_the_Bayou_[1742].mp4","filesize":1762970601,"file_ext":"mp4","md5":"63a0c6c3859f1a32ccaafa8013c7ab9c"},{"name":"2017-03-10_RE7_7_-_Brawl_in_the_Bayou_[1742].png","filesize":241291,"file_ext":"png","md5":"c058df1b186e2bfad8e50dad6d1c7f86"}]}},{"id":1741,"type":"episode","attributes":{"title":"RE7 #8 - I'm on a boat and it's 107 proof","slug":"backwardz-compatible-2017-re7-8","number":9,"description":"What was supposed to be a V.R. fueled scream fest has turned into a drunken rage as Kyle and Miles fight, shoot, and peg their way through the wreckage that brought Mia and Eveline to the Baker's back yard. What secrets will they find? How many shots will they take? What does it feel like to have whiskey that's 54% alcohol burn your lungs? All of that and more will be answered on this episode of Backwardz Compatible.","length":3862,"original_air_date":"2017-03-17T20:00:00.000Z","channel_id":"92b6bb21-91d2-4b1b-bf95-3268fa0d9939","channel_slug":"rooster-teeth","season_id":"ffa323b7-464d-11e7-a302-065410f210c4","season_slug":"backwardz-compatible-2017","season_number":4,"show_title":"Backwardz Compatible","show_id":"ff93ec57-464d-11e7-a302-065410f210c4","show_slug":"backwardz-compatible","is_sponsors_only":true},"uuid":"00576388-464e-11e7-a302-065410f210c4","archive":{"id":"roosterteeth-1741","status":"archived","files":[{"name":"2017-03-17_RE7_8_-_Im_on_a_boat_and_its_107_proof_[1741].description","filesize":420,"file_ext":"description","md5":"b8e2c2c6923ee443c9811d7682e141ff"},{"name":"2017-03-17_RE7_8_-_Im_on_a_boat_and_its_107_proof_[1741].info.json","filesize":20200,"file_ext":"json","md5":"6f9dc9920f1bac4040b15382cfda7969"},{"name":"2017-03-17_RE7_8_-_Im_on_a_boat_and_its_107_proof_[1741].mp4","filesize":2027405061,"file_ext":"mp4","md5":"ea2f6869e3dc55daa41f0c1dd81e1844"},{"name":"2017-03-17_RE7_8_-_Im_on_a_boat_and_its_107_proof_[1741].png","filesize":242183,"file_ext":"png","md5":"51a8d5a1a8824013affccdbf3e123fa2"}]}},{"id":1740,"type":"episode","attributes":{"title":"RE7 #9 - What Are? What is?","slug":"backwardz-compatible-2017-re7-9-what-are-what-is","number":10,"description":"Kyle and Miles make their way through the derelict ship that brought Mia and Eveline to the Baker's back door. What secrets will they find? How many Larry's will they peg? What's it like to have a homeless guy yell at you in the middle of a laundromat? All of this and more will be answered on this episode of Backwardz Compatible!","length":3822,"original_air_date":"2017-03-24T20:00:00.000Z","channel_id":"92b6bb21-91d2-4b1b-bf95-3268fa0d9939","channel_slug":"rooster-teeth","season_id":"ffa323b7-464d-11e7-a302-065410f210c4","season_slug":"backwardz-compatible-2017","season_number":4,"show_title":"Backwardz Compatible","show_id":"ff93ec57-464d-11e7-a302-065410f210c4","show_slug":"backwardz-compatible","is_sponsors_only":true},"uuid":"0057ee03-464e-11e7-a302-065410f210c4","archive":{"id":"roosterteeth-1740","status":"archived","files":[{"name":"2017-03-24_RE7_9_-_What_Are_What_is_[1740].description","filesize":331,"file_ext":"description","md5":"52912fe0cd6ff1c03f26c232dfa4ca91"},{"name":"2017-03-24_RE7_9_-_What_Are_What_is_[1740].info.json","filesize":20121,"file_ext":"json","md5":"7b32818fad28dc736efd22d6a9e83301"},{"name":"2017-03-24_RE7_9_-_What_Are_What_is_[1740].mp4","filesize":1997298677,"file_ext":"mp4","md5":"50b8de9e9c4b59f9979a2a5aa0ecd947"},{"name":"2017-03-24_RE7_9_-_What_Are_What_is_[1740].png","filesize":241553,"file_ext":"png","md5":"1cfacb8929c3f075c263f4283bf52b1a"}]}},{"id":1739,"type":"episode","attributes":{"title":"RE7 #10 - E-001","slug":"backwardz-compatible-2017-re7-10","number":11,"description":"Kyle and Miles have fought their way through the ship and now stand at the entrance to the salt mines. The secrets to Eveline, Mia, and the Baker's are hidden somewhere down there and if they find them then hopefully they will discover a way to stop Evie. One thing is for sure, it ends tonight. Join our hapless duo as they make their way through the last episode of the RE7 campaign","length":3937,"original_air_date":"2017-03-31T20:00:00.000Z","channel_id":"92b6bb21-91d2-4b1b-bf95-3268fa0d9939","channel_slug":"rooster-teeth","season_id":"ffa323b7-464d-11e7-a302-065410f210c4","season_slug":"backwardz-compatible-2017","season_number":4,"show_title":"Backwardz Compatible","show_id":"ff93ec57-464d-11e7-a302-065410f210c4","show_slug":"backwardz-compatible","is_sponsors_only":true},"uuid":"00590ad3-464e-11e7-a302-065410f210c4","archive":{"id":"roosterteeth-1739","status":"archived","files":[{"name":"2017-03-31_RE7_10_-_E-001_[1739].description","filesize":384,"file_ext":"description","md5":"0dbb37dcf1e18f29c7e96b72038ce9d1"},{"name":"2017-03-31_RE7_10_-_E-001_[1739].info.json","filesize":20095,"file_ext":"json","md5":"d291dca55f5fb9dabfc07805ce2704f2"},{"name":"2017-03-31_RE7_10_-_E-001_[1739].mp4","filesize":2044343556,"file_ext":"mp4","md5":"ba00769e36703b3ae12f170e4c9780f2"},{"name":"2017-03-31_RE7_10_-_E-001_[1739].png","filesize":242111,"file_ext":"png","md5":"a814e792010ce00a00aa8bb822776fd3"}]}},{"id":1738,"type":"episode","attributes":{"title":"Sonic Adventure 2, #1 - Gotta Go Fast!","slug":"backwardz-compatible-2017-sa2-1","number":12,"description":"Could it be? Has it finally happened? Are Miles and Kyle going to play THE greatest Sonic game ever made? That's right Backwardz Compatible will be bringing you the blistering speed of Sonic and Shadow, the hard hitting mech action of Tails and Dr. Eggman, plus all of the high flying, treasure hunting action of Knuckles and Rouge. Did I mention Chaos? Cause there is gonna be plenty of Chaos. Strap yourselves in because it's Sonic Adventure 2 on Backwardz Compatible.","length":3500,"original_air_date":"2017-04-07T20:00:00.000Z","channel_id":"92b6bb21-91d2-4b1b-bf95-3268fa0d9939","channel_slug":"rooster-teeth","season_id":"ffa323b7-464d-11e7-a302-065410f210c4","season_slug":"backwardz-compatible-2017","season_number":4,"show_title":"Backwardz Compatible","show_id":"ff93ec57-464d-11e7-a302-065410f210c4","show_slug":"backwardz-compatible","is_sponsors_only":true},"uuid":"00597161-464e-11e7-a302-065410f210c4","archive":{"id":"roosterteeth-1738","status":"archived","files":[{"name":"2017-04-07_Sonic_Adventure_2_1_-_Gotta_Go_Fast_[1738].description","filesize":470,"file_ext":"description","md5":"43341560690f22e39777f3ed6c53464c"},{"name":"2017-04-07_Sonic_Adventure_2_1_-_Gotta_Go_Fast_[1738].info.json","filesize":20240,"file_ext":"json","md5":"630f2746388f00a6b4ab7e198d584b11"},{"name":"2017-04-07_Sonic_Adventure_2_1_-_Gotta_Go_Fast_[1738].mp4","filesize":1814719481,"file_ext":"mp4","md5":"dc160acfab57a8bf91039397180822b4"},{"name":"2017-04-07_Sonic_Adventure_2_1_-_Gotta_Go_Fast_[1738].png","filesize":421816,"file_ext":"png","md5":"e8cc297d68680eddb0d4a127170ae917"}]}},{"id":27550,"type":"episode","attributes":{"title":"Sonic Adventure 2, #2 - Parenting 101","slug":"backwardz-compatible-2017-sonic-2","number":13,"description":"Kyle and Miles ponder one of life's great mysteries. \"Is that Knuckles hand or is it a glove?\" and \"If it's a glove, what does his hand look like?!\" They then show why Knuckles should win Father of the year.","length":3303,"original_air_date":"2017-04-14T20:00:00.000Z","channel_id":"92b6bb21-91d2-4b1b-bf95-3268fa0d9939","channel_slug":"rooster-teeth","season_id":"ffa323b7-464d-11e7-a302-065410f210c4","season_slug":"backwardz-compatible-2017","season_number":4,"show_title":"Backwardz Compatible","show_id":"ff93ec57-464d-11e7-a302-065410f210c4","show_slug":"backwardz-compatible","is_sponsors_only":true},"uuid":"0059f196-464e-11e7-a302-065410f210c4","archive":{"id":"roosterteeth-27550","status":"archived","files":[{"name":"2017-04-14_Sonic_Adventure_2_2_-_Parenting_101_[27550].description","filesize":207,"file_ext":"description","md5":"04ec5b481fce1f4c36ffc857995096dd"},{"name":"2017-04-14_Sonic_Adventure_2_2_-_Parenting_101_[27550].info.json","filesize":19985,"file_ext":"json","md5":"fe29ad9074c6316c4c51d4daf38ed4de"},{"name":"2017-04-14_Sonic_Adventure_2_2_-_Parenting_101_[27550].mp4","filesize":1684016304,"file_ext":"mp4","md5":"4ba2fe5409bcef965fdcda4c63f67563"},{"name":"2017-04-14_Sonic_Adventure_2_2_-_Parenting_101_[27550].png","filesize":422190,"file_ext":"png","md5":"5d1852b87b892edab8338ee663d4e243"}]}},{"id":1736,"type":"episode","attributes":{"title":"Sonic Adventure 2, #3 - #Eyebrows4Cheng","slug":"backwardz-compatible-2017-sonic-adventure-2-3","number":14,"description":"3D Animator Melanie Stern joins Kyle in berating and ridiculing Miles parenting methods. Will she be able to enlighten Miles and change his ways or will he forever be just a monster of a parent? Tune in to find out in this episode of Backwardz Compatible!","length":4494,"original_air_date":"2017-04-21T20:00:00.000Z","channel_id":"92b6bb21-91d2-4b1b-bf95-3268fa0d9939","channel_slug":"rooster-teeth","season_id":"ffa323b7-464d-11e7-a302-065410f210c4","season_slug":"backwardz-compatible-2017","season_number":4,"show_title":"Backwardz Compatible","show_id":"ff93ec57-464d-11e7-a302-065410f210c4","show_slug":"backwardz-compatible","is_sponsors_only":true},"uuid":"005a4c66-464e-11e7-a302-065410f210c4","archive":{"id":"roosterteeth-1736","status":"archived","files":[{"name":"2017-04-21_Sonic_Adventure_2_3_-_Eyebrows4Cheng_[1736].description","filesize":255,"file_ext":"description","md5":"28fdcae86af63fce72e2a7f6f09c5321"},{"name":"2017-04-21_Sonic_Adventure_2_3_-_Eyebrows4Cheng_[1736].info.json","filesize":20066,"file_ext":"json","md5":"e4139cab9687d65c89976a83aea7edb2"},{"name":"2017-04-21_Sonic_Adventure_2_3_-_Eyebrows4Cheng_[1736].mp4","filesize":2356056510,"file_ext":"mp4","md5":"ae72ba29c8da6fd125e28ec46f6265ef"},{"name":"2017-04-21_Sonic_Adventure_2_3_-_Eyebrows4Cheng_[1736].png","filesize":422235,"file_ext":"png","md5":"af8f6040dbb92b1b768183fa3dd7f1e2"}]}},{"id":1735,"type":"episode","attributes":{"title":"Sonic Adventure 2, #4 - Rage So Hard","slug":"backwardz-compatible-2017-sonic-adventure-2-4-rage-so-hard","number":15,"description":"Kyle and Miles start this week off right with a big ol' boss battle. They're getting close to the end of the Hero story and the pressure is high. Sometimes when the pressure is that high and you fail it's frustrating. Sometimes frustration turns into rage. Sometimes that rage then erupts violently on poor unsuspecting water bottles. What does all of this mean? Just watch to find out.","length":4141,"original_air_date":"2017-04-28T20:00:00.000Z","channel_id":"92b6bb21-91d2-4b1b-bf95-3268fa0d9939","channel_slug":"rooster-teeth","season_id":"ffa323b7-464d-11e7-a302-065410f210c4","season_slug":"backwardz-compatible-2017","season_number":4,"show_title":"Backwardz Compatible","show_id":"ff93ec57-464d-11e7-a302-065410f210c4","show_slug":"backwardz-compatible","is_sponsors_only":true},"uuid":"005af0f6-464e-11e7-a302-065410f210c4","archive":{"id":"roosterteeth-1735","status":"archived","files":[{"name":"2017-04-28_Sonic_Adventure_2_4_-_Rage_So_Hard_[1735].description","filesize":386,"file_ext":"description","md5":"211b361a7f8b6f793dbe48064b5db592"},{"name":"2017-04-28_Sonic_Adventure_2_4_-_Rage_So_Hard_[1735].info.json","filesize":20227,"file_ext":"json","md5":"f873741789fe71be8e644ebe222d2db4"},{"name":"2017-04-28_Sonic_Adventure_2_4_-_Rage_So_Hard_[1735].mp4","filesize":2166181922,"file_ext":"mp4","md5":"d2d773b9ca2b3891635ce2c52209ab5b"},{"name":"2017-04-28_Sonic_Adventure_2_4_-_Rage_So_Hard_[1735].png","filesize":421212,"file_ext":"png","md5":"6bd0340746ffb5e48dea428bd7af04cc"}]}},{"id":1734,"type":"episode","attributes":{"title":"Sonic Adventure 2, #5 - The Dark Side","slug":"backwardz-compatible-2017-sonic-adventure-2-5","number":16,"description":"Kyle and Miles have one Final Rush before they can play the Dark Story but standing between them and glory is the Edge Lord himself Shadow. Can Kyle and Miles defeat the embodiment of cool? Will Damian grow up to be a well adjusted Chao? What does a hedgehog penis look like? All of this and more will be answered in this episode of Backwardz Compatible.","length":3813,"original_air_date":"2017-05-05T20:00:00.000Z","channel_id":"92b6bb21-91d2-4b1b-bf95-3268fa0d9939","channel_slug":"rooster-teeth","season_id":"ffa323b7-464d-11e7-a302-065410f210c4","season_slug":"backwardz-compatible-2017","season_number":4,"show_title":"Backwardz Compatible","show_id":"ff93ec57-464d-11e7-a302-065410f210c4","show_slug":"backwardz-compatible","is_sponsors_only":true},"uuid":"005c17db-464e-11e7-a302-065410f210c4","archive":{"id":"roosterteeth-1734","status":"archived","files":[{"name":"2017-05-05_Sonic_Adventure_2_5_-_The_Dark_Side_[1734].description","filesize":354,"file_ext":"description","md5":"c4770c288aa46f50d5aae0f5c7902cb7"},{"name":"2017-05-05_Sonic_Adventure_2_5_-_The_Dark_Side_[1734].info.json","filesize":20159,"file_ext":"json","md5":"29abd1890944c6b9d90431b9e1739739"},{"name":"2017-05-05_Sonic_Adventure_2_5_-_The_Dark_Side_[1734].mp4","filesize":1998398294,"file_ext":"mp4","md5":"ae8a5832247475db6fc287b9e705b550"},{"name":"2017-05-05_Sonic_Adventure_2_5_-_The_Dark_Side_[1734].png","filesize":421747,"file_ext":"png","md5":"b82098e343d5233418dc10d84369320a"}]}},{"id":1733,"type":"episode","attributes":{"title":"Sonic Adventure 2, #6 - Who are all these people?","slug":"backwardz-compatible-2017-sonic-adventure-2-6","number":17,"description":"Kyle and Miles are joined by Crunchyroll's Victoria Holden aka @SailorBee aka Shadow's gf 4 life and she brought a whole entourage of people with her.","length":3383,"original_air_date":"2017-05-12T20:00:00.000Z","channel_id":"92b6bb21-91d2-4b1b-bf95-3268fa0d9939","channel_slug":"rooster-teeth","season_id":"ffa323b7-464d-11e7-a302-065410f210c4","season_slug":"backwardz-compatible-2017","season_number":4,"show_title":"Backwardz Compatible","show_id":"ff93ec57-464d-11e7-a302-065410f210c4","show_slug":"backwardz-compatible","is_sponsors_only":true},"uuid":"005c8f89-464e-11e7-a302-065410f210c4","archive":{"id":"roosterteeth-1733","status":"archived","files":[{"name":"2017-05-12_Sonic_Adventure_2_6_-_Who_are_all_these_people_[1733].description","filesize":150,"file_ext":"description","md5":"8af6096e863b67fcc39da1cf54d67eb7"},{"name":"2017-05-12_Sonic_Adventure_2_6_-_Who_are_all_these_people_[1733].info.json","filesize":19995,"file_ext":"json","md5":"6e1e3d716e060d07b6c4e219db591d55"},{"name":"2017-05-12_Sonic_Adventure_2_6_-_Who_are_all_these_people_[1733].mp4","filesize":1770364678,"file_ext":"mp4","md5":"cff32511b3902aaba1563f77e9d85d47"},{"name":"2017-05-12_Sonic_Adventure_2_6_-_Who_are_all_these_people_[1733].png","filesize":399661,"file_ext":"png","md5":"599a2bc10d2ce1188229e3e851887669"}]}},{"id":1732,"type":"episode","attributes":{"title":"Sonic Adventure 2, #7 - No One Between Us","slug":"backwardz-compatible-2017-sonic-adventure-2-7-no-one-between-us","number":18,"description":"Kyle and Miles are tearing through the Dark Story, gush about the big news from Sonic Forces, and find the Wal Mart of military bases but when it looks like everything is going so well they decide to sing a duet and blow their load early. Maybe they were too excited after they found a picture of Sonic's original girlfriend Madonna.","length":4068,"original_air_date":"2017-05-19T20:00:00.000Z","channel_id":"92b6bb21-91d2-4b1b-bf95-3268fa0d9939","channel_slug":"rooster-teeth","season_id":"ffa323b7-464d-11e7-a302-065410f210c4","season_slug":"backwardz-compatible-2017","season_number":4,"show_title":"Backwardz Compatible","show_id":"ff93ec57-464d-11e7-a302-065410f210c4","show_slug":"backwardz-compatible","is_sponsors_only":true},"uuid":"005d1335-464e-11e7-a302-065410f210c4","archive":{"id":"roosterteeth-1732","status":"archived","files":[{"name":"2017-05-19_Sonic_Adventure_2_7_-_No_One_Between_Us_[1732].description","filesize":333,"file_ext":"description","md5":"be2f95a9326d3341fec94ccb754457c7"},{"name":"2017-05-19_Sonic_Adventure_2_7_-_No_One_Between_Us_[1732].info.json","filesize":20210,"file_ext":"json","md5":"31901f6f7d1af4f9d3678ae8f1854ea6"},{"name":"2017-05-19_Sonic_Adventure_2_7_-_No_One_Between_Us_[1732].mp4","filesize":2127694746,"file_ext":"mp4","md5":"80e0b01019e525beab2ccb27e3bc22c6"},{"name":"2017-05-19_Sonic_Adventure_2_7_-_No_One_Between_Us_[1732].png","filesize":422514,"file_ext":"png","md5":"dd85c177e66fa74bc5e6dcc3495fa076"}]}},{"id":1731,"type":"episode","attributes":{"title":"Sonic Adventure 2, #8 - Word Association","slug":"backwardz-compatible-2017-sonic-adventure-2-8-word-association","number":19,"description":"Kyle and Miles are finally, FINALLY reaching the end of the Dark Story. Hopefully Miles gets his spine popped back in place so they can finish this one right.","length":2810,"original_air_date":"2017-05-26T20:00:00.000Z","channel_id":"92b6bb21-91d2-4b1b-bf95-3268fa0d9939","channel_slug":"rooster-teeth","season_id":"ffa323b7-464d-11e7-a302-065410f210c4","season_slug":"backwardz-compatible-2017","season_number":4,"show_title":"Backwardz Compatible","show_id":"ff93ec57-464d-11e7-a302-065410f210c4","show_slug":"backwardz-compatible","is_sponsors_only":true},"uuid":"005da2e2-464e-11e7-a302-065410f210c4","archive":{"id":"roosterteeth-1731","status":"archived","files":[{"name":"2017-05-26_Sonic_Adventure_2_8_-_Word_Association_[1731].description","filesize":158,"file_ext":"description","md5":"91a289f8d3bde854e71a372297713b20"},{"name":"2017-05-26_Sonic_Adventure_2_8_-_Word_Association_[1731].info.json","filesize":20027,"file_ext":"json","md5":"2f8e6b144ad74ca0e53ce333471ae4f0"},{"name":"2017-05-26_Sonic_Adventure_2_8_-_Word_Association_[1731].mp4","filesize":1442809479,"file_ext":"mp4","md5":"c100888602b7953940bb3e8267303177"},{"name":"2017-05-26_Sonic_Adventure_2_8_-_Word_Association_[1731].png","filesize":422070,"file_ext":"png","md5":"d53f855dad7b5a77b470326e9e37d214"}]}},{"id":1730,"type":"episode","attributes":{"title":"Sonic Adventure 2, #9 - All the Upgrades","slug":"backwardz-compatible-2017-sonic-adventure-2-9-all-the-upgrades","number":20,"description":"As many of you have pointed out the boys are missing some upgrades. So Kyle and Miles have made the decision to get all the upgrades that matter.","length":3722,"original_air_date":"2017-06-02T20:00:00.000Z","channel_id":"92b6bb21-91d2-4b1b-bf95-3268fa0d9939","channel_slug":"rooster-teeth","season_id":"ffa323b7-464d-11e7-a302-065410f210c4","season_slug":"backwardz-compatible-2017","season_number":4,"show_title":"Backwardz Compatible","show_id":"ff93ec57-464d-11e7-a302-065410f210c4","show_slug":"backwardz-compatible","is_sponsors_only":true},"uuid":"27984f12-c906-4447-a812-527e62c5f5b7","archive":{"id":"roosterteeth-1730","status":"archived","files":[{"name":"2017-06-02_Sonic_Adventure_2_9_-_All_the_Upgrades_[1730].description","filesize":145,"file_ext":"description","md5":"880e646552e97efe26015d58de84dae6"},{"name":"2017-06-02_Sonic_Adventure_2_9_-_All_the_Upgrades_[1730].info.json","filesize":20016,"file_ext":"json","md5":"386ee0398730c93b5b26921c47fe4a4a"},{"name":"2017-06-02_Sonic_Adventure_2_9_-_All_the_Upgrades_[1730].mp4","filesize":1945681548,"file_ext":"mp4","md5":"85dbdb06fc0fd36fa69f0416257726d1"},{"name":"2017-06-02_Sonic_Adventure_2_9_-_All_the_Upgrades_[1730].png","filesize":422120,"file_ext":"png","md5":"59259d0b713a9826c60576f1c580f926"}]}},{"id":1728,"type":"episode","attributes":{"title":"Sonic Adventure 2, #10 - Last Story","slug":"backwardz-compatible-2017-sonic-adventure-2-10","number":21,"description":"It's all been leading to this. What was the warning Dr. Eggman got at the end of the Dark Story? What's going to happen if Sonic Already destroyed the Eclipse Cannon? What happened to Shadow on space colony Ark before Eggman found him? All of this and more will be answered on this final episode of Sonic Adventure 2!","length":3203,"original_air_date":"2017-06-09T20:00:00.000Z","channel_id":"92b6bb21-91d2-4b1b-bf95-3268fa0d9939","channel_slug":"rooster-teeth","season_id":"ffa323b7-464d-11e7-a302-065410f210c4","season_slug":"backwardz-compatible-2017","season_number":4,"show_title":"Backwardz Compatible","show_id":"ff93ec57-464d-11e7-a302-065410f210c4","show_slug":"backwardz-compatible","is_sponsors_only":true},"uuid":"9e5c00cb-23f0-4925-b87e-c293f6db2be2","archive":{"id":"roosterteeth-1728","status":"archived","files":[{"name":"2017-06-09_Sonic_Adventure_2_10_-_Last_Story_[1728].description","filesize":317,"file_ext":"description","md5":"4736cddd08845a813902015be2adc1f9"},{"name":"2017-06-09_Sonic_Adventure_2_10_-_Last_Story_[1728].info.json","filesize":20128,"file_ext":"json","md5":"8c30fe391bd9dc30b4c9439954db83aa"},{"name":"2017-06-09_Sonic_Adventure_2_10_-_Last_Story_[1728].mp4","filesize":1654537650,"file_ext":"mp4","md5":"8db7218019dcbaae5bed340b60ef3927"},{"name":"2017-06-09_Sonic_Adventure_2_10_-_Last_Story_[1728].png","filesize":427621,"file_ext":"png","md5":"6c2c8b019502f640f835a8664817cadc"}]}},{"id":1729,"type":"episode","attributes":{"title":"One Off: Battlesloths 2025","slug":"backwardz-compatible-2017-one-off-battlesloths-2025","number":22,"description":"Kyle and Miles are still deciding on a new game series so why not play a fun one off while they make a decision? Gray Haddock and Josh Ornelas join our intrepid duo for a fun and chaotic game of Battlesloths 2025: The Great Pizza Wars. Shout out to developer Invisible Collective for making this game! The publisher is pretty cool too.","length":3848,"original_air_date":"2017-06-16T21:00:00.000Z","channel_id":"92b6bb21-91d2-4b1b-bf95-3268fa0d9939","channel_slug":"rooster-teeth","season_id":"ffa323b7-464d-11e7-a302-065410f210c4","season_slug":"backwardz-compatible-2017","season_number":4,"show_title":"Backwardz Compatible","show_id":"ff93ec57-464d-11e7-a302-065410f210c4","show_slug":"backwardz-compatible","is_sponsors_only":true},"uuid":"f8fd622b-af04-408a-b0e7-f7f7340662f4","archive":{"id":"roosterteeth-1729","status":"archived","files":[{"name":"2017-06-16_One_Off_Battlesloths_2025_[1729].description","filesize":335,"file_ext":"description","md5":"d81fcb774f90fbc3dfcb39e66f9ce307"},{"name":"2017-06-16_One_Off_Battlesloths_2025_[1729].info.json","filesize":20096,"file_ext":"json","md5":"e30f90d1d59c43f1728e5a315c153074"},{"name":"2017-06-16_One_Off_Battlesloths_2025_[1729].mp4","filesize":2020667385,"file_ext":"mp4","md5":"e9de25c7bdeff460eb2dab9f3c2a352f"},{"name":"2017-06-16_One_Off_Battlesloths_2025_[1729].png","filesize":451114,"file_ext":"png","md5":"e1e95c3951b46a3ad6bd947c2a01276e"}]}},{"id":1727,"type":"episode","attributes":{"title":"DMC3, #1 - A Crazy Party","slug":"backwardz-compatible-2017-dmc3-part-1","number":23,"description":"Kyle and Miles have been invited to one crazy party filled with half demons, full demons, a sibling rivalry, a sky whale, a crazy lady on a motorcycle, and a world destroying tower. Not to mention one guy with more quips, puns and one liners than all of Arnold Schwarzenegger's movies combined. If things sound crazy don't worry, just sit down, turn the volume up and let's rock!","length":3548,"original_air_date":"2017-06-23T21:00:00.000Z","channel_id":"92b6bb21-91d2-4b1b-bf95-3268fa0d9939","channel_slug":"rooster-teeth","season_id":"ffa323b7-464d-11e7-a302-065410f210c4","season_slug":"backwardz-compatible-2017","season_number":4,"show_title":"Backwardz Compatible","show_id":"ff93ec57-464d-11e7-a302-065410f210c4","show_slug":"backwardz-compatible","is_sponsors_only":true},"uuid":"d7ae8768-0fbf-430c-a449-955e7b3c2365","archive":{"id":"roosterteeth-1727","status":"archived","files":[{"name":"2017-06-23_DMC3_1_-_A_Crazy_Party_[1727].description","filesize":379,"file_ext":"description","md5":"3ac3aaa0407b257b9f42ea2b93322cd2"},{"name":"2017-06-23_DMC3_1_-_A_Crazy_Party_[1727].info.json","filesize":20125,"file_ext":"json","md5":"900f99b133276cc0006ce2c47d489a11"},{"name":"2017-06-23_DMC3_1_-_A_Crazy_Party_[1727].mp4","filesize":1857874816,"file_ext":"mp4","md5":"85a9cb8adbfafdd68bdc0bc2fc74ee8c"},{"name":"2017-06-23_DMC3_1_-_A_Crazy_Party_[1727].png","filesize":290524,"file_ext":"png","md5":"04c011721aebcedd9e8e8aaa433ba67a"}]}},{"id":1725,"type":"episode","attributes":{"title":"DMC3, #2 - A Soul of Steel","slug":"backwardz-compatible-2017-dm-c3-2-a-soul-of-steel","number":24,"description":"While Kyle and Miles run around on their demon massacre they talk about the oft forgotten brother to Dante and Vergil.","length":3472,"original_air_date":"2017-06-30T21:00:00.000Z","channel_id":"92b6bb21-91d2-4b1b-bf95-3268fa0d9939","channel_slug":"rooster-teeth","season_id":"ffa323b7-464d-11e7-a302-065410f210c4","season_slug":"backwardz-compatible-2017","season_number":4,"show_title":"Backwardz Compatible","show_id":"ff93ec57-464d-11e7-a302-065410f210c4","show_slug":"backwardz-compatible","is_sponsors_only":true},"uuid":"4a907ff1-d4f8-4a38-b5b5-7cbbecb337d0","archive":{"id":"roosterteeth-1725","status":"archived","files":[{"name":"2017-06-30_DMC3_2_-_A_Soul_of_Steel_[1725].description","filesize":118,"file_ext":"description","md5":"894022bc26c65623440a4405af96aadb"},{"name":"2017-06-30_DMC3_2_-_A_Soul_of_Steel_[1725].info.json","filesize":19906,"file_ext":"json","md5":"89d20b2da7dfb09259e2f05dd1b06670"},{"name":"2017-06-30_DMC3_2_-_A_Soul_of_Steel_[1725].mp4","filesize":1815855458,"file_ext":"mp4","md5":"ee3b45f4c0bece595fcf0db6870c88ce"},{"name":"2017-06-30_DMC3_2_-_A_Soul_of_Steel_[1725].png","filesize":298164,"file_ext":"png","md5":"85b1c6de4537d3482236e93e850fa4f3"}]}},{"id":1726,"type":"episode","attributes":{"title":"DMC3, #3 - Role Play","slug":"backwardz-compatible-2017-dm-c3-3","number":25,"description":"Kyle and Miles continue their ascent to the top of Temen-ni-gru and along their way they discuss how best to role play a Batman villain...in the bedroom.","length":3190,"original_air_date":"2017-07-07T21:00:00.000Z","channel_id":"92b6bb21-91d2-4b1b-bf95-3268fa0d9939","channel_slug":"rooster-teeth","season_id":"ffa323b7-464d-11e7-a302-065410f210c4","season_slug":"backwardz-compatible-2017","season_number":4,"show_title":"Backwardz Compatible","show_id":"ff93ec57-464d-11e7-a302-065410f210c4","show_slug":"backwardz-compatible","is_sponsors_only":true},"uuid":"401ffc64-d0c1-4cd4-84f9-c4051cf80e9a","archive":{"id":"roosterteeth-1726","status":"archived","files":[{"name":"2017-07-07_DMC3_3_-_Role_Play_[1726].description","filesize":153,"file_ext":"description","md5":"4c2ce2b5fb109ccd561b15605485561b"},{"name":"2017-07-07_DMC3_3_-_Role_Play_[1726].info.json","filesize":19875,"file_ext":"json","md5":"1f6f43dd742303a0ed8e9b9ed68a164f"},{"name":"2017-07-07_DMC3_3_-_Role_Play_[1726].mp4","filesize":1671006877,"file_ext":"mp4","md5":"10963195b6b1637b460b9ec8f80da7aa"},{"name":"2017-07-07_DMC3_3_-_Role_Play_[1726].png","filesize":291496,"file_ext":"png","md5":"15a3d7e50b0ec4adaa6ae1fe73d593d7"}]}},{"id":1724,"type":"episode","attributes":{"title":"DMC3, #4 - Attic Metal","slug":"backwardz-compatible-2017-dm-c3-4-attic-metal","number":26,"description":"Kyle and Miles are joined by Editor and Producer, Cole Gallian. Whille Cole entertains Miles with stories about his new house, Kyle runs into some trouble with a voluptuous Vampire.","length":4252,"original_air_date":"2017-07-14T21:00:00.000Z","channel_id":"92b6bb21-91d2-4b1b-bf95-3268fa0d9939","channel_slug":"rooster-teeth","season_id":"ffa323b7-464d-11e7-a302-065410f210c4","season_slug":"backwardz-compatible-2017","season_number":4,"show_title":"Backwardz Compatible","show_id":"ff93ec57-464d-11e7-a302-065410f210c4","show_slug":"backwardz-compatible","is_sponsors_only":true},"uuid":"310d94f3-54b3-4648-8e01-b876ba99c39b","archive":{"id":"roosterteeth-1724","status":"archived","files":[{"name":"2017-07-14_DMC3_4_-_Attic_Metal_[1724].description","filesize":181,"file_ext":"description","md5":"cb880478d1d157cac1ebe3de663f762d"},{"name":"2017-07-14_DMC3_4_-_Attic_Metal_[1724].info.json","filesize":19972,"file_ext":"json","md5":"4d6da42e36c2f607570de949cb4df10d"},{"name":"2017-07-14_DMC3_4_-_Attic_Metal_[1724].mp4","filesize":2224470354,"file_ext":"mp4","md5":"d0171b7d1db1deb02e349320e849854a"},{"name":"2017-07-14_DMC3_4_-_Attic_Metal_[1724].png","filesize":288497,"file_ext":"png","md5":"5871421a0a19a125627e897e64503ee0"}]}},{"id":1722,"type":"episode","attributes":{"title":"Dream Daddy","slug":"backwardz-compatible-2017-dream-daddy","number":27,"description":"Athletic Dad, Coffee Shop Dad, Rich Dad, Dad Dad. So many Dads and so little time but Kyle and Miles want to meet them all in the hopes of finding the perfect Dad.","length":4629,"original_air_date":"2017-08-09T21:00:00.000Z","channel_id":"92b6bb21-91d2-4b1b-bf95-3268fa0d9939","channel_slug":"rooster-teeth","season_id":"ffa323b7-464d-11e7-a302-065410f210c4","season_slug":"backwardz-compatible-2017","season_number":4,"show_title":"Backwardz Compatible","show_id":"ff93ec57-464d-11e7-a302-065410f210c4","show_slug":"backwardz-compatible","is_sponsors_only":true},"uuid":"ec1e1fa0-68e5-4699-9980-77d75ac923fa","archive":{"id":"roosterteeth-1722","status":"archived","files":[{"name":"2017-08-09_Dream_Daddy_[1722].description","filesize":163,"file_ext":"description","md5":"47f3594583232574398a63cd19b541be"},{"name":"2017-08-09_Dream_Daddy_[1722].info.json","filesize":19817,"file_ext":"json","md5":"f27ae64e196611ec3223704a6745884d"},{"name":"2017-08-09_Dream_Daddy_[1722].mp4","filesize":2434229417,"file_ext":"mp4","md5":"5bdb21fd0332946b0d63852d2506b577"},{"name":"2017-08-09_Dream_Daddy_[1722].png","filesize":268208,"file_ext":"png","md5":"9300fd2a990fac178d65f3ad1f691744"}]}},{"id":1723,"type":"episode","attributes":{"title":"DMC3, #5 - Dante Daddy","slug":"backwardz-compatible-2017-dm-c3-5","number":28,"description":"Kyle and Miles pickup right where they left off with DMC3. This episode is full of bosses, post RTX stories, a special appearance by \"Michael Caine\", and that good old wise crackin' Dante.","length":3626,"original_air_date":"2017-07-28T21:00:00.000Z","channel_id":"92b6bb21-91d2-4b1b-bf95-3268fa0d9939","channel_slug":"rooster-teeth","season_id":"ffa323b7-464d-11e7-a302-065410f210c4","season_slug":"backwardz-compatible-2017","season_number":4,"show_title":"Backwardz Compatible","show_id":"ff93ec57-464d-11e7-a302-065410f210c4","show_slug":"backwardz-compatible","is_sponsors_only":true},"uuid":"74e56df8-4ff9-46fc-a9ea-672f561ae636","archive":{"id":"roosterteeth-1723","status":"archived","files":[{"name":"2017-07-28_DMC3_5_-_Dante_Daddy_[1723].description","filesize":188,"file_ext":"description","md5":"573c7ae2034024673f0489cf34224816"},{"name":"2017-07-28_DMC3_5_-_Dante_Daddy_[1723].info.json","filesize":19920,"file_ext":"json","md5":"2c1d9f6a83407a4ee041df14b1f4d468"},{"name":"2017-07-28_DMC3_5_-_Dante_Daddy_[1723].mp4","filesize":1897557087,"file_ext":"mp4","md5":"6a86a8f94f15265f38ee828827cc988f"},{"name":"2017-07-28_DMC3_5_-_Dante_Daddy_[1723].png","filesize":297865,"file_ext":"png","md5":"7802653252a72a4331d71f6dc01a8419"}]}},{"id":1721,"type":"episode","attributes":{"title":"DMC3, #6 - The Dick That Fucks The World","slug":"backwardz-compatible-2017-dm-c3-6-the-dick-that-fucks-the-world","number":29,"description":"They started from the bottom, then went to the top, and now they're at the bottom again. Kyle and Miles don't know what Temen-ni-gru has in store for them...but the Jester does.","length":3866,"original_air_date":"2017-08-04T21:00:00.000Z","channel_id":"92b6bb21-91d2-4b1b-bf95-3268fa0d9939","channel_slug":"rooster-teeth","season_id":"ffa323b7-464d-11e7-a302-065410f210c4","season_slug":"backwardz-compatible-2017","season_number":4,"show_title":"Backwardz Compatible","show_id":"ff93ec57-464d-11e7-a302-065410f210c4","show_slug":"backwardz-compatible","is_sponsors_only":true},"uuid":"fc0e41d6-69a9-48c0-ab54-e5f33a49de1e","archive":{"id":"roosterteeth-1721","status":"archived","files":[{"name":"2017-08-04_DMC3_6_-_The_Dick_That_Fucks_The_World_[1721].description","filesize":177,"file_ext":"description","md5":"84cc1f39a5c11780bda431b078ed5f27"},{"name":"2017-08-04_DMC3_6_-_The_Dick_That_Fucks_The_World_[1721].info.json","filesize":20051,"file_ext":"json","md5":"87e1adefded4b254e0f9997c6453c231"},{"name":"2017-08-04_DMC3_6_-_The_Dick_That_Fucks_The_World_[1721].mp4","filesize":2022716772,"file_ext":"mp4","md5":"3063737e18fd0e45c135f15d85570527"},{"name":"2017-08-04_DMC3_6_-_The_Dick_That_Fucks_The_World_[1721].png","filesize":291724,"file_ext":"png","md5":"2f87c12d8ed75947dae6aef24d49a69f"}]}},{"id":1720,"type":"episode","attributes":{"title":"DMC3, #7 - Bedroom Eyes","slug":"backwardz-compatible-2017-dm-c3-7","number":30,"description":"While Arkham is busy opening the portal to the demon world, Kyle tells Miles about the other Star Wars smuggler, Dash Rendar.","length":3161,"original_air_date":"2017-08-11T21:00:00.000Z","channel_id":"92b6bb21-91d2-4b1b-bf95-3268fa0d9939","channel_slug":"rooster-teeth","season_id":"ffa323b7-464d-11e7-a302-065410f210c4","season_slug":"backwardz-compatible-2017","season_number":4,"show_title":"Backwardz Compatible","show_id":"ff93ec57-464d-11e7-a302-065410f210c4","show_slug":"backwardz-compatible","is_sponsors_only":true},"uuid":"7e5ffe03-3fc6-4967-8321-c0bfed42d788","archive":{"id":"roosterteeth-1720","status":"archived","files":[{"name":"2017-08-11_DMC3_7_-_Bedroom_Eyes_[1720].description","filesize":125,"file_ext":"description","md5":"09dbd2b28cc016210fc174cfab70d4c0"},{"name":"2017-08-11_DMC3_7_-_Bedroom_Eyes_[1720].info.json","filesize":19856,"file_ext":"json","md5":"fe254a2fe4d50e100a931807b8c6d48d"},{"name":"2017-08-11_DMC3_7_-_Bedroom_Eyes_[1720].mp4","filesize":1649797621,"file_ext":"mp4","md5":"66350be6460b28afce8b88568aec1f40"},{"name":"2017-08-11_DMC3_7_-_Bedroom_Eyes_[1720].png","filesize":290856,"file_ext":"png","md5":"d8818676fe68ad840d832fb636d3802e"}]}},{"id":1719,"type":"episode","attributes":{"title":"DMC3, #8 - Demonic Chess","slug":"backwardz-compatible-2017-demonic-chess","number":31,"description":"Kyle and Miles finally reach the top of Temen-ni-gru and enter the portal to the demon world. What would you expect to greet them? Demons? Tortured souls? Lucifer himself? What awaits is much more sinister, a giant game of chess. Where's Ron Weasley when you need him?","length":3019,"original_air_date":"2017-08-18T21:00:00.000Z","channel_id":"92b6bb21-91d2-4b1b-bf95-3268fa0d9939","channel_slug":"rooster-teeth","season_id":"ffa323b7-464d-11e7-a302-065410f210c4","season_slug":"backwardz-compatible-2017","season_number":4,"show_title":"Backwardz Compatible","show_id":"ff93ec57-464d-11e7-a302-065410f210c4","show_slug":"backwardz-compatible","is_sponsors_only":true},"uuid":"0b3b066a-bf1f-4fd7-a266-238720357c8c","archive":{"id":"roosterteeth-1719","status":"archived","files":[{"name":"2017-08-18_DMC3_8_-_Demonic_Chess_[1719].description","filesize":268,"file_ext":"description","md5":"489b490a28107ae14b9440512db99c76"},{"name":"2017-08-18_DMC3_8_-_Demonic_Chess_[1719].info.json","filesize":20020,"file_ext":"json","md5":"0c1c2e3cad50a288bdac1609a6259294"},{"name":"2017-08-18_DMC3_8_-_Demonic_Chess_[1719].mp4","filesize":1585211178,"file_ext":"mp4","md5":"49bbd0cf7ee57b4914016305fed22b13"},{"name":"2017-08-18_DMC3_8_-_Demonic_Chess_[1719].png","filesize":292035,"file_ext":"png","md5":"a9fbd56297cc92255c2a7dbd9622ecf9"}]}},{"id":1718,"type":"episode","attributes":{"title":"DMC3, #9 - Boss Rush","slug":"backwardz-compatible-2017-dm-c3-9","number":32,"description":"Like any classic game, when you get close to the end, sometimes you have to face off with each boss you've defeated up to that point one more time. As if their hands weren't full enough, Kyle and Miles decide they want to play a game of \"Would you rather?\" to make things a little more interesting. So ask yourselves this, would you rather give up oral sex (giving and receiving) or give up cheese?","length":3644,"original_air_date":"2017-08-25T21:00:00.000Z","channel_id":"92b6bb21-91d2-4b1b-bf95-3268fa0d9939","channel_slug":"rooster-teeth","season_id":"ffa323b7-464d-11e7-a302-065410f210c4","season_slug":"backwardz-compatible-2017","season_number":4,"show_title":"Backwardz Compatible","show_id":"ff93ec57-464d-11e7-a302-065410f210c4","show_slug":"backwardz-compatible","is_sponsors_only":true},"uuid":"cc9aa037-7fd5-4cdc-964c-2683b67cb8aa","archive":{"id":"roosterteeth-1718","status":"archived","files":[{"name":"2017-08-25_DMC3_9_-_Boss_Rush_[1718].description","filesize":398,"file_ext":"description","md5":"e55d088aa465238e8410819345d37637"},{"name":"2017-08-25_DMC3_9_-_Boss_Rush_[1718].info.json","filesize":20124,"file_ext":"json","md5":"2e4360b68c0dcf6edea370398067091d"},{"name":"2017-08-25_DMC3_9_-_Boss_Rush_[1718].mp4","filesize":1900802334,"file_ext":"mp4","md5":"92b5656a9fff08dffbc3ee5dc3e016d0"},{"name":"2017-08-25_DMC3_9_-_Boss_Rush_[1718].png","filesize":291597,"file_ext":"png","md5":"ddab3409f4937e8e1b90d97847934a04"}]}},{"id":1717,"type":"episode","attributes":{"title":"DMC3, #10 - Two Brothers","slug":"backwardz-compatible-2017-dm-c3-10","number":33,"description":"This is it, the last two missions for DMC3! Everything has been building to this moment, the sky whale, the fight with the Jester, driving a motorcycle up the side of a building, the giant chess game, getting shot in the head, getting stabbed in the chest, and let's not forget the desecration of a beloved pizza slice. Finally Kyle and Miles will face off with Arkham, confront Vergil, and close the portal to the demon world...hopefully.","length":4618,"original_air_date":"2017-09-01T21:00:00.000Z","channel_id":"92b6bb21-91d2-4b1b-bf95-3268fa0d9939","channel_slug":"rooster-teeth","season_id":"ffa323b7-464d-11e7-a302-065410f210c4","season_slug":"backwardz-compatible-2017","season_number":4,"show_title":"Backwardz Compatible","show_id":"ff93ec57-464d-11e7-a302-065410f210c4","show_slug":"backwardz-compatible","is_sponsors_only":true},"uuid":"731c3963-b806-4018-8be2-9b3952e6ce2a","archive":{"id":"roosterteeth-1717","status":"archived","files":[{"name":"2017-09-01_DMC3_10_-_Two_Brothers_[1717].description","filesize":439,"file_ext":"description","md5":"37a1c7c33b3f9f70b84ddd76e40719a3"},{"name":"2017-09-01_DMC3_10_-_Two_Brothers_[1717].info.json","filesize":20178,"file_ext":"json","md5":"a1685f27c54199d706856be459b61843"},{"name":"2017-09-01_DMC3_10_-_Two_Brothers_[1717].mp4","filesize":2396836844,"file_ext":"mp4","md5":"ee735bcbec5d1594cedc8fa58893e46b"},{"name":"2017-09-01_DMC3_10_-_Two_Brothers_[1717].png","filesize":292468,"file_ext":"png","md5":"cffc0e92956fd8b417b115583bd8c53e"}]}},{"id":1716,"type":"episode","attributes":{"title":"DreadOut #1 - Definitely Not Fatal Frame","slug":"backwardz-compatible-2017-dm-c3-11","number":34,"description":"It's under 90 degrees outside and in Texas that means it's fall and fall means it's time for some scary games. Indonesian horror game DreadOut made waves when it was first released so Miles bought it on Steam; problem is he was never brave enough to play it by himself so he brought it to Backwardz Compatible so Kyle can join in his misery.","length":3051,"original_air_date":"2017-09-08T21:00:00.000Z","channel_id":"92b6bb21-91d2-4b1b-bf95-3268fa0d9939","channel_slug":"rooster-teeth","season_id":"ffa323b7-464d-11e7-a302-065410f210c4","season_slug":"backwardz-compatible-2017","season_number":4,"show_title":"Backwardz Compatible","show_id":"ff93ec57-464d-11e7-a302-065410f210c4","show_slug":"backwardz-compatible","is_sponsors_only":true},"uuid":"0f1c1c6f-5c7d-46d8-963b-210b5d386f37","archive":{"id":"roosterteeth-1716","status":"archived","files":[{"name":"2017-09-08_DreadOut_1_-_Definitely_Not_Fatal_Frame_[1716].description","filesize":341,"file_ext":"description","md5":"d46f1da18dda941e6e3fa858088da28f"},{"name":"2017-09-08_DreadOut_1_-_Definitely_Not_Fatal_Frame_[1716].info.json","filesize":20116,"file_ext":"json","md5":"5f5c28e8a26a3009d92d071db591ad5a"},{"name":"2017-09-08_DreadOut_1_-_Definitely_Not_Fatal_Frame_[1716].jpg","filesize":374629,"file_ext":"jpg","md5":"0ce8edbdee02c7c6b66525b5391e81eb"},{"name":"2017-09-08_DreadOut_1_-_Definitely_Not_Fatal_Frame_[1716].mp4","filesize":1598758833,"file_ext":"mp4","md5":"eab908c9fe43e7be4281e0963099d70c"}]}},{"id":1715,"type":"episode","attributes":{"title":"DreadOut #2 - Get Schwifty","slug":"backwardz-compatible-2017-dread-out-2-get-schwifty","number":35,"description":"It's Friday, you're done for the day, it's time to sit down, relax, and enjoy some videos right? That may be true for everyone else in the world but Kyle and Miles got after school detention. For what? I don't know, but what I do know is that the teacher forgot about our boys and locked them in for the night. So now Kyle and Miles have to brave a school haunted by a pig, some white haired harlot, and a principal with mental issues. The only thing standing between them and these ferocious phantoms is the camera on their smartphone. I hope they brought a charger.","length":3374,"original_air_date":"2017-09-15T21:00:00.000Z","channel_id":"92b6bb21-91d2-4b1b-bf95-3268fa0d9939","channel_slug":"rooster-teeth","season_id":"ffa323b7-464d-11e7-a302-065410f210c4","season_slug":"backwardz-compatible-2017","season_number":4,"show_title":"Backwardz Compatible","show_id":"ff93ec57-464d-11e7-a302-065410f210c4","show_slug":"backwardz-compatible","is_sponsors_only":true},"uuid":"5a302b42-cc03-450e-93dc-4b11a92f095b","archive":{"id":"roosterteeth-1715","status":"archived","files":[{"name":"2017-09-15_DreadOut_2_-_Get_Schwifty_[1715].description","filesize":567,"file_ext":"description","md5":"328d3ecfeafd9b9dc1c5e3fbdb6cbb2e"},{"name":"2017-09-15_DreadOut_2_-_Get_Schwifty_[1715].info.json","filesize":20363,"file_ext":"json","md5":"4acd2f98828289be2f0a7884e7eb3a36"},{"name":"2017-09-15_DreadOut_2_-_Get_Schwifty_[1715].jpg","filesize":374449,"file_ext":"jpg","md5":"8913b69695b6fa8c329e2646dfa4aaa4"},{"name":"2017-09-15_DreadOut_2_-_Get_Schwifty_[1715].mp4","filesize":1770895076,"file_ext":"mp4","md5":"9681f0efe69a1bbdbd50195fbed46558"}]}},{"id":1714,"type":"episode","attributes":{"title":"DreadOut #3 - Lenny G","slug":"backwardz-compatible-2017-dread-out-3","number":36,"description":"Kyle and Miles have obtained the scissors, the ONLY thing that can cut rope apparently. Now nothing is stopping them from going to the front of the school and using the keys to open the door. Oh, TOTALLY unrelated but how do you feel about swarms of locus and/or rats crawling on your face?","length":3176,"original_air_date":"2017-09-22T23:00:00.000Z","channel_id":"92b6bb21-91d2-4b1b-bf95-3268fa0d9939","channel_slug":"rooster-teeth","season_id":"ffa323b7-464d-11e7-a302-065410f210c4","season_slug":"backwardz-compatible-2017","season_number":4,"show_title":"Backwardz Compatible","show_id":"ff93ec57-464d-11e7-a302-065410f210c4","show_slug":"backwardz-compatible","is_sponsors_only":true},"uuid":"c35a713f-ef77-4fb3-9bad-8dd6245a4a9b","archive":{"id":"roosterteeth-1714","status":"archived","files":[{"name":"2017-09-22_DreadOut_3_-_Lenny_G_[1714].description","filesize":290,"file_ext":"description","md5":"aa2ef4161ed364b8e8065f2a3fd1f0fa"},{"name":"2017-09-22_DreadOut_3_-_Lenny_G_[1714].info.json","filesize":20032,"file_ext":"json","md5":"f0237e6f96b14f4ba5857ada656e3fd5"},{"name":"2017-09-22_DreadOut_3_-_Lenny_G_[1714].jpg","filesize":349785,"file_ext":"jpg","md5":"f258d3585cafae08b2c3f7264c6dc757"},{"name":"2017-09-22_DreadOut_3_-_Lenny_G_[1714].mp4","filesize":1663611876,"file_ext":"mp4","md5":"881001a55c34bd52e89d0d349d4b1b3b"}]}},{"id":1713,"type":"episode","attributes":{"title":"DreadOut #4 - Mirror, Mirror, on the Wall","slug":"backwardz-compatible-2017-dread-out-4","number":37,"description":"Kyle and Miles have fought ghosts, and they have run from ghosts, but did they ever consider trying to sit down and talk to a ghost? Maybe these ghosts are just misunderstood, maybe the woman in the red dress just wants to be friends, maybe the ghost that killed Doni was just trying to give him a neck massage and her hand slipped, I don't know, but what I do know is that this is the last episode of DreadOut.","length":5659,"original_air_date":"2017-09-29T21:00:00.000Z","channel_id":"92b6bb21-91d2-4b1b-bf95-3268fa0d9939","channel_slug":"rooster-teeth","season_id":"ffa323b7-464d-11e7-a302-065410f210c4","season_slug":"backwardz-compatible-2017","season_number":4,"show_title":"Backwardz Compatible","show_id":"ff93ec57-464d-11e7-a302-065410f210c4","show_slug":"backwardz-compatible","is_sponsors_only":true},"uuid":"8c2ae1b6-73ed-4de3-8df8-f5b94285569f","archive":{"id":"roosterteeth-1713","status":"archived","files":[{"name":"2017-09-29_DreadOut_4_-_Mirror_Mirror_on_the_Wall_[1713].description","filesize":411,"file_ext":"description","md5":"26438d5e9749cf405eddaa8386442b77"},{"name":"2017-09-29_DreadOut_4_-_Mirror_Mirror_on_the_Wall_[1713].info.json","filesize":20050,"file_ext":"json","md5":"524c9da610016bcd00210d961994c415"},{"name":"2017-09-29_DreadOut_4_-_Mirror_Mirror_on_the_Wall_[1713].jpg","filesize":374482,"file_ext":"jpg","md5":"8edc8b390bbcc3ab3019c31ff38c95b7"},{"name":"2017-09-29_DreadOut_4_-_Mirror_Mirror_on_the_Wall_[1713].mp4","filesize":2964464235,"file_ext":"mp4","md5":"7138f44303a77fb60504150b3c719163"}]}},{"id":1712,"type":"episode","attributes":{"title":"Spooky's Jump Scare Mansion","slug":"backwardz-compatible-2017-spooky-s-jump-scare-mansion","number":38,"description":"It's October and things are getting a little spooky around the office, some might say 2Spooky. Our boys are playing a different spooky game every week in October. This week it's Spooky's Jump Scare Mansion. I know this looks cute and delightful now but trust me, things are not always what they seem.","length":3341,"original_air_date":"2017-10-06T21:00:00.000Z","channel_id":"92b6bb21-91d2-4b1b-bf95-3268fa0d9939","channel_slug":"rooster-teeth","season_id":"ffa323b7-464d-11e7-a302-065410f210c4","season_slug":"backwardz-compatible-2017","season_number":4,"show_title":"Backwardz Compatible","show_id":"ff93ec57-464d-11e7-a302-065410f210c4","show_slug":"backwardz-compatible","is_sponsors_only":true},"uuid":"7621e411-e8ca-4fb8-a719-bee270a21e90","archive":{"id":"roosterteeth-1712","status":"archived","files":[{"name":"2017-10-06_Spookys_Jump_Scare_Mansion_[1712].description","filesize":300,"file_ext":"description","md5":"68aaf2ea96050eef4ab33b4150552ce8"},{"name":"2017-10-06_Spookys_Jump_Scare_Mansion_[1712].info.json","filesize":19928,"file_ext":"json","md5":"2eefdf94bf53586ecf8aa8b75c7f5f2d"},{"name":"2017-10-06_Spookys_Jump_Scare_Mansion_[1712].mp4","filesize":1750875042,"file_ext":"mp4","md5":"a07910fdb70e3a45b8a1312bb2445aed"},{"name":"2017-10-06_Spookys_Jump_Scare_Mansion_[1712].png","filesize":198999,"file_ext":"png","md5":"c5c69e7fd9e77ccef678ebf718bf5794"}]}},{"id":1711,"type":"episode","attributes":{"title":"Bendy and the Ink Machine","slug":"backwardz-compatible-2017-bendy-and-the-ink-machine","number":39,"description":"2Spooky October continues with Bendy and the Ink Machine! What horrors will Kyle and Miles find in the inky black heart of this once beloved animation studio? Monsters? Ghouls? Or the scariest thing of all...a sprint button that doesn't work?!","length":7964,"original_air_date":"2017-10-13T22:00:00.000Z","channel_id":"92b6bb21-91d2-4b1b-bf95-3268fa0d9939","channel_slug":"rooster-teeth","season_id":"ffa323b7-464d-11e7-a302-065410f210c4","season_slug":"backwardz-compatible-2017","season_number":4,"show_title":"Backwardz Compatible","show_id":"ff93ec57-464d-11e7-a302-065410f210c4","show_slug":"backwardz-compatible","is_sponsors_only":true},"uuid":"f9e827e9-2527-4805-a903-fc4d9765e909","archive":{"id":"roosterteeth-1711","status":"archived","files":[{"name":"2017-10-13_Bendy_and_the_Ink_Machine_[1711].description","filesize":243,"file_ext":"description","md5":"e80497dc21b9681206dc960c66bdedf9"},{"name":"2017-10-13_Bendy_and_the_Ink_Machine_[1711].info.json","filesize":19851,"file_ext":"json","md5":"038a7701d4e3aba9f05616e658aeaadf"},{"name":"2017-10-13_Bendy_and_the_Ink_Machine_[1711].jpg","filesize":288316,"file_ext":"jpg","md5":"421f59208bb64d987643a140b585353e"},{"name":"2017-10-13_Bendy_and_the_Ink_Machine_[1711].mp4","filesize":4174362117,"file_ext":"mp4","md5":"75e4871d7a4c008f9101cb16d72dd305"}]}},{"id":1710,"type":"episode","attributes":{"title":"Alien Isolation: Last Survivor","slug":"backwardz-compatible-2017-alien-isolation","number":40,"description":"2Spooky October brings Kyle and Miles back to the Nostromo, back to the stress, the fear, the crushing anxiety. It brings them back to their lovely and deadly Xenomorph named Scoops. Poor Scoops has had no one to play with for a whole year, I wonder if he'll be excited to see Kyle and Miles? I know our boys will be screaming when they see Scoops.","length":4101,"original_air_date":"2017-10-20T21:00:00.000Z","channel_id":"92b6bb21-91d2-4b1b-bf95-3268fa0d9939","channel_slug":"rooster-teeth","season_id":"ffa323b7-464d-11e7-a302-065410f210c4","season_slug":"backwardz-compatible-2017","season_number":4,"show_title":"Backwardz Compatible","show_id":"ff93ec57-464d-11e7-a302-065410f210c4","show_slug":"backwardz-compatible","is_sponsors_only":true},"uuid":"0258f970-1862-4e73-8d78-48cde4c9f684","archive":{"id":"roosterteeth-1710","status":"archived","files":[{"name":"2017-10-20_Alien_Isolation_Last_Survivor_[1710].description","filesize":348,"file_ext":"description","md5":"7f8188b671a64febd474c0dd017a5bf3"},{"name":"2017-10-20_Alien_Isolation_Last_Survivor_[1710].info.json","filesize":20146,"file_ext":"json","md5":"15de9761e10e93d9d9ae91227bf68a94"},{"name":"2017-10-20_Alien_Isolation_Last_Survivor_[1710].mp4","filesize":2155606583,"file_ext":"mp4","md5":"6da20a59af157183d3d08772d330f7f9"},{"name":"2017-10-20_Alien_Isolation_Last_Survivor_[1710].png","filesize":173172,"file_ext":"png","md5":"d9f4b03ba6a16afeac32eab311a4cb35"}]}},{"id":1709,"type":"episode","attributes":{"title":"Layers of Fear","slug":"backwardz-compatible-2017-layers-of-fear","number":41,"description":"2Spooky October has to come to an end. So why not do it with a nice exploration game right? That's what Kyle and Miles thought anyway, but they got more than they bargained for. What mysteries does this old house hold? What happened to the painters wife and child? What \"master piece\" awaits under all the layers of this man's past? All I'll say is that the clench factor is astoundingly high in this game.","length":3312,"original_air_date":"2017-10-27T21:00:00.000Z","channel_id":"92b6bb21-91d2-4b1b-bf95-3268fa0d9939","channel_slug":"rooster-teeth","season_id":"ffa323b7-464d-11e7-a302-065410f210c4","season_slug":"backwardz-compatible-2017","season_number":4,"show_title":"Backwardz Compatible","show_id":"ff93ec57-464d-11e7-a302-065410f210c4","show_slug":"backwardz-compatible","is_sponsors_only":true},"uuid":"f85f052c-7a1c-47ac-8399-55bcc0d07799","archive":{"id":"roosterteeth-1709","status":"archived","files":[{"name":"2017-10-27_Layers_of_Fear_[1709].description","filesize":406,"file_ext":"description","md5":"867303ebf52377f85dfe47b6120f9f8f"},{"name":"2017-10-27_Layers_of_Fear_[1709].info.json","filesize":20153,"file_ext":"json","md5":"b552da2ae3fa5154dc5bb91cdb5927c3"},{"name":"2017-10-27_Layers_of_Fear_[1709].jpg","filesize":356452,"file_ext":"jpg","md5":"3d16516d5c4751a2db04892fd83b040b"},{"name":"2017-10-27_Layers_of_Fear_[1709].mp4","filesize":1735674200,"file_ext":"mp4","md5":"8cb7b66b413dbc3d4a36acf9e39165b6"}]}},{"id":1708,"type":"episode","attributes":{"title":"Layers of Fear - #2","slug":"backwardz-compatible-2017-layers-of-fear-2","number":42,"description":"I know, I know, it's November and the card at the beginning says 2Spooky October but listen, our boys filmed this on Halloween and insisted it still counts. After everything they have been through and all the years they surely shaved off their lives from filming this part I think we can let it slide because this is without a doubt the scariest thing Kyle and Miles have played for Backwardz Compatible.","length":8354,"original_air_date":"2017-11-03T23:00:00.000Z","channel_id":"92b6bb21-91d2-4b1b-bf95-3268fa0d9939","channel_slug":"rooster-teeth","season_id":"ffa323b7-464d-11e7-a302-065410f210c4","season_slug":"backwardz-compatible-2017","season_number":4,"show_title":"Backwardz Compatible","show_id":"ff93ec57-464d-11e7-a302-065410f210c4","show_slug":"backwardz-compatible","is_sponsors_only":true},"uuid":"e3a8cdfa-bbe2-4e01-b57d-4d378a76b621","archive":{"id":"roosterteeth-1708","status":"archived","files":[{"name":"2017-11-03_Layers_of_Fear_-_2_[1708].description","filesize":404,"file_ext":"description","md5":"592a52a48f8dc0b1fd87533f64183184"},{"name":"2017-11-03_Layers_of_Fear_-_2_[1708].info.json","filesize":20002,"file_ext":"json","md5":"003c7915d0d8fd470d597f09cbe04bc6"},{"name":"2017-11-03_Layers_of_Fear_-_2_[1708].jpg","filesize":356039,"file_ext":"jpg","md5":"a53ea9b7d5d0037861f59d012b33c703"},{"name":"2017-11-03_Layers_of_Fear_-_2_[1708].mp4","filesize":4378949548,"file_ext":"mp4","md5":"711c18a72e11600dbc7b9fb72b62444c"}]}},{"id":1707,"type":"episode","attributes":{"title":"Layers of Fear - Inheritance DLC","slug":"backwardz-compatible-2017-layers-of-fear-3","number":43,"description":"Our boys thought they were done but oh how they were wrong. Years after the main game finished the painter's daughter returns to her childhood home in search of answers but unfortunately for Kyle and Miles the daughter may have inherited more from her father than just thisdecrepit oldhouse.","length":4662,"original_air_date":"2017-11-10T22:00:00.000Z","channel_id":"92b6bb21-91d2-4b1b-bf95-3268fa0d9939","channel_slug":"rooster-teeth","season_id":"ffa323b7-464d-11e7-a302-065410f210c4","season_slug":"backwardz-compatible-2017","season_number":4,"show_title":"Backwardz Compatible","show_id":"ff93ec57-464d-11e7-a302-065410f210c4","show_slug":"backwardz-compatible","is_sponsors_only":true},"uuid":"8b43cd57-da7c-4176-bcfc-4f119a882e63","archive":{"id":"roosterteeth-1707","status":"archived","files":[{"name":"2017-11-10_Layers_of_Fear_-_Inheritance_DLC_[1707].description","filesize":295,"file_ext":"description","md5":"1d36740dc4136c009aae52ed88b362f4"},{"name":"2017-11-10_Layers_of_Fear_-_Inheritance_DLC_[1707].info.json","filesize":19932,"file_ext":"json","md5":"2bd9a90efabe9b1ee27de7ed9bfe9ecd"},{"name":"2017-11-10_Layers_of_Fear_-_Inheritance_DLC_[1707].jpg","filesize":356295,"file_ext":"jpg","md5":"f4d53acad883aaa3259be556ce66a80e"},{"name":"2017-11-10_Layers_of_Fear_-_Inheritance_DLC_[1707].mp4","filesize":2443745550,"file_ext":"mp4","md5":"35e252de409cb6c48d3d6dad225211ac"}]}},{"id":1706,"type":"episode","attributes":{"title":"Shovel Knight","slug":"backwardz-compatible-2017-shovel-knight","number":44,"description":"Huzzah and greetings eager viewers. Join our intrepid young adventurers as they take up their shovels and journey to defeat the evil Enchantress. Bandits, monsters, rats on propellers, and the Order of No Quarter stand between our heroes and the Tower of Fate where the Enchantress resides. Can our boys make it through these challenges or will they end up being each others downfall? Only time will tell.","length":3557,"original_air_date":"2017-11-18T01:00:00.000Z","channel_id":"92b6bb21-91d2-4b1b-bf95-3268fa0d9939","channel_slug":"rooster-teeth","season_id":"ffa323b7-464d-11e7-a302-065410f210c4","season_slug":"backwardz-compatible-2017","season_number":4,"show_title":"Backwardz Compatible","show_id":"ff93ec57-464d-11e7-a302-065410f210c4","show_slug":"backwardz-compatible","is_sponsors_only":true},"uuid":"3116d517-6907-4855-811d-1a78eaa368e7","archive":{"id":"roosterteeth-1706","status":"archived","files":[{"name":"2017-11-18_Shovel_Knight_[1706].description","filesize":405,"file_ext":"description","md5":"9a660080af246c118730439709418362"},{"name":"2017-11-18_Shovel_Knight_[1706].info.json","filesize":19974,"file_ext":"json","md5":"97d2a7d7d9a459cf68c3ad04c0018d3c"},{"name":"2017-11-18_Shovel_Knight_[1706].jpg","filesize":312773,"file_ext":"jpg","md5":"f1d62474d9531bb84b4e522df63c1373"},{"name":"2017-11-18_Shovel_Knight_[1706].mp4","filesize":1860779700,"file_ext":"mp4","md5":"71769c9d833eb08d846c6b1f3702416d"}]}},{"id":1705,"type":"episode","attributes":{"title":"Shovel Knight #2 - Fairy of Shovelry","slug":"backwardz-compatible-2017-shovel-knight-2","number":45,"description":"","length":3229,"original_air_date":"2017-11-24T22:00:00.000Z","channel_id":"92b6bb21-91d2-4b1b-bf95-3268fa0d9939","channel_slug":"rooster-teeth","season_id":"ffa323b7-464d-11e7-a302-065410f210c4","season_slug":"backwardz-compatible-2017","season_number":4,"show_title":"Backwardz Compatible","show_id":"ff93ec57-464d-11e7-a302-065410f210c4","show_slug":"backwardz-compatible","is_sponsors_only":true},"uuid":"1d9ead45-6420-46e3-97e5-7f3ce14482f1","archive":{"id":"roosterteeth-1705","status":"archived","files":[{"name":"2017-11-24_Shovel_Knight_2_-_Fairy_of_Shovelry_[1705].description","filesize":0,"file_ext":"description","md5":"d41d8cd98f00b204e9800998ecf8427e"},{"name":"2017-11-24_Shovel_Knight_2_-_Fairy_of_Shovelry_[1705].info.json","filesize":19649,"file_ext":"json","md5":"522940e2ea77f245a04f344b78758fbc"},{"name":"2017-11-24_Shovel_Knight_2_-_Fairy_of_Shovelry_[1705].jpg","filesize":313668,"file_ext":"jpg","md5":"d4b5af5228b6ec81a95819de3865c6ea"},{"name":"2017-11-24_Shovel_Knight_2_-_Fairy_of_Shovelry_[1705].mp4","filesize":1696506049,"file_ext":"mp4","md5":"8431e12f6c5e972dad0b73dc40ebc10e"}]}},{"id":1704,"type":"episode","attributes":{"title":"Shovel Knight #3 - The Cream of the Crop","slug":"backwardz-compatible-2017-shovel-knight-3","number":46,"description":"Kyle and Miles come across the unrivaled Baz, trade blows with the sub-aquatic Treasure Knight, and cross shovels with the cold hearted Polar Knight.","length":3568,"original_air_date":"2017-12-01T22:00:00.000Z","channel_id":"92b6bb21-91d2-4b1b-bf95-3268fa0d9939","channel_slug":"rooster-teeth","season_id":"ffa323b7-464d-11e7-a302-065410f210c4","season_slug":"backwardz-compatible-2017","season_number":4,"show_title":"Backwardz Compatible","show_id":"ff93ec57-464d-11e7-a302-065410f210c4","show_slug":"backwardz-compatible","is_sponsors_only":true},"uuid":"04ee5d9b-9990-4460-b30f-2bbe4194d4f9","archive":{"id":"roosterteeth-1704","status":"archived","files":[{"name":"2017-12-01_Shovel_Knight_3_-_The_Cream_of_the_Crop_[1704].description","filesize":149,"file_ext":"description","md5":"0ee87480329a558378254f55c6878ea4"},{"name":"2017-12-01_Shovel_Knight_3_-_The_Cream_of_the_Crop_[1704].info.json","filesize":19810,"file_ext":"json","md5":"c2a788b24e21d9111899ef33e7d00c95"},{"name":"2017-12-01_Shovel_Knight_3_-_The_Cream_of_the_Crop_[1704].jpg","filesize":313908,"file_ext":"jpg","md5":"a3b2023f6a9ff8098b5e13aa7f163c3f"},{"name":"2017-12-01_Shovel_Knight_3_-_The_Cream_of_the_Crop_[1704].mp4","filesize":1867368155,"file_ext":"mp4","md5":"12105c53f58f0caed29a0e0d073e6d9e"}]}},{"id":1703,"type":"episode","attributes":{"title":"Shovel Knight #4 - This Armor was a Mistake","slug":"backwardz-compatible-2017-shovel-knight-4","number":47,"description":"Single screen co-op games can be a lot of fun. They can also be the most infuriating test of friendship two people can experience. This is one of those times.....the latter not the former. Shut up you knew what I meant.","length":3122,"original_air_date":"2017-12-08T22:00:00.000Z","channel_id":"92b6bb21-91d2-4b1b-bf95-3268fa0d9939","channel_slug":"rooster-teeth","season_id":"ffa323b7-464d-11e7-a302-065410f210c4","season_slug":"backwardz-compatible-2017","season_number":4,"show_title":"Backwardz Compatible","show_id":"ff93ec57-464d-11e7-a302-065410f210c4","show_slug":"backwardz-compatible","is_sponsors_only":true},"uuid":"0b868573-2ff6-48e1-b253-bfa0c800671a","archive":{"id":"roosterteeth-1703","status":"archived","files":[{"name":"2017-12-08_Shovel_Knight_4_-_This_Armor_was_a_Mistake_[1703].description","filesize":219,"file_ext":"description","md5":"687140eb9e347b8c420a1940432bd6c5"},{"name":"2017-12-08_Shovel_Knight_4_-_This_Armor_was_a_Mistake_[1703].info.json","filesize":19889,"file_ext":"json","md5":"0b47e1b98126d8e1a49e9a1166f7b457"},{"name":"2017-12-08_Shovel_Knight_4_-_This_Armor_was_a_Mistake_[1703].jpg","filesize":313096,"file_ext":"jpg","md5":"e6b7ee2a78321ae35205748ac182fbaf"},{"name":"2017-12-08_Shovel_Knight_4_-_This_Armor_was_a_Mistake_[1703].mp4","filesize":1632128140,"file_ext":"mp4","md5":"f08782129b1fd4324db452d7fb120d32"}]}},{"id":1702,"type":"episode","attributes":{"title":"Shovel Knight #5 - Gold Boi","slug":"backwardz-compatible-2017-gold-boi","number":48,"description":"The time has come, our boys have faced off with every Knight in the Order of No Quarter and now the only thing that stands in their way is The Enchantress and her Tower. Will Kyle and Miles overcome their challenges and avenge their good friend Shield Knight or will they fall never to rise again? One thing's for sure, they're gonna look fly as hell while doing it.","length":4704,"original_air_date":"2017-12-15T23:00:00.000Z","channel_id":"92b6bb21-91d2-4b1b-bf95-3268fa0d9939","channel_slug":"rooster-teeth","season_id":"ffa323b7-464d-11e7-a302-065410f210c4","season_slug":"backwardz-compatible-2017","season_number":4,"show_title":"Backwardz Compatible","show_id":"ff93ec57-464d-11e7-a302-065410f210c4","show_slug":"backwardz-compatible","is_sponsors_only":true},"uuid":"f9ddc702-57f9-4562-9e9b-c8dd13de0e8a","archive":{"id":"roosterteeth-1702","status":"archived","files":[{"name":"2017-12-15_Shovel_Knight_5_-_Gold_Boi_[1702].description","filesize":366,"file_ext":"description","md5":"a6b6ae85e33205805699a0213b6eb4fd"},{"name":"2017-12-15_Shovel_Knight_5_-_Gold_Boi_[1702].info.json","filesize":19979,"file_ext":"json","md5":"7f4c93335d102b85492ab6b6bb3b3fe4"},{"name":"2017-12-15_Shovel_Knight_5_-_Gold_Boi_[1702].jpg","filesize":313420,"file_ext":"jpg","md5":"2fe9905d26d7bdd6f2600c3bf0b0c63e"},{"name":"2017-12-15_Shovel_Knight_5_-_Gold_Boi_[1702].mp4","filesize":2446424715,"file_ext":"mp4","md5":"40778ae98ee419d4829f1ec629f436c6"}]}},{"id":1701,"type":"episode","attributes":{"title":"RE7 - Not a Hero","slug":"backwardz-compatible-2017-re7-not-a-hero","number":49,"description":"It has almost been a year since Kyle and Miles put on the shoes of Ethan Winters and took on the foul creatures that inhabited the Baker Estate. At the end of their journey they were promised a new adventure with series mainstay Chris Redfield set for the spring. Cut back to now, it's the middle of winter and our boys can finally get their hands on that sweet, sweet, Chris Redfield DLC that they have been waiting for. Join them as they take on the sick and twisted games that Lucas Baker has concocted and hopefully figure out why Chris Redfield is working for Umbrella.","length":3681,"original_air_date":"2017-12-22T22:00:00.000Z","channel_id":"92b6bb21-91d2-4b1b-bf95-3268fa0d9939","channel_slug":"rooster-teeth","season_id":"ffa323b7-464d-11e7-a302-065410f210c4","season_slug":"backwardz-compatible-2017","season_number":4,"show_title":"Backwardz Compatible","show_id":"ff93ec57-464d-11e7-a302-065410f210c4","show_slug":"backwardz-compatible","is_sponsors_only":true},"uuid":"962f8b45-f842-4e34-b117-f74b264b4350","archive":{"id":"roosterteeth-1701","status":"archived","files":[{"name":"2017-12-22_RE7_-_Not_a_Hero_[1701].description","filesize":574,"file_ext":"description","md5":"fac91e75f40397d8b80b5adb4d5c5ba4"},{"name":"2017-12-22_RE7_-_Not_a_Hero_[1701].info.json","filesize":20147,"file_ext":"json","md5":"50bbdcf0c8913aa016a42492744925e3"},{"name":"2017-12-22_RE7_-_Not_a_Hero_[1701].jpg","filesize":242110,"file_ext":"jpg","md5":"5e03351b3b3e304d607ac8861d4d1ce2"},{"name":"2017-12-22_RE7_-_Not_a_Hero_[1701].mp4","filesize":1927531741,"file_ext":"mp4","md5":"45a9bead8be3f9315dee1d64ad4ea7c4"}]}},{"id":1700,"type":"episode","attributes":{"title":"RE7 - I.C.P.","slug":"backwardz-compatible-2017-i-c-p","number":50,"description":"Kyle and Miles have a bomb strapped to their wrist, an I.C.P. loving mad man on the loose, and mold, so much mold growing everywhere in this mine. Our boys better grab some bleach and get to cleaning because this DLC is barreling towards it's conclusion. (Stick around after the credits because our boys get an exclusive play through of a Claire Redfield \"Secret Mission\".)","length":2836,"original_air_date":"2017-12-29T22:00:00.000Z","channel_id":"92b6bb21-91d2-4b1b-bf95-3268fa0d9939","channel_slug":"rooster-teeth","season_id":"ffa323b7-464d-11e7-a302-065410f210c4","season_slug":"backwardz-compatible-2017","season_number":4,"show_title":"Backwardz Compatible","show_id":"ff93ec57-464d-11e7-a302-065410f210c4","show_slug":"backwardz-compatible","is_sponsors_only":true},"uuid":"0c267d58-42b0-4358-8493-9bd25aae3b52","archive":{"id":"roosterteeth-1700","status":"archived","files":[{"name":"2017-12-29_RE7_-_I.C.P._[1700].description","filesize":373,"file_ext":"description","md5":"fa801761a587ee6536a299a7bdfb7353"},{"name":"2017-12-29_RE7_-_I.C.P._[1700].info.json","filesize":19892,"file_ext":"json","md5":"5eef9b44f88064e199cc846b9334bb03"},{"name":"2017-12-29_RE7_-_I.C.P._[1700].jpg","filesize":254252,"file_ext":"jpg","md5":"07c4e46d95a85eb5ad326c3775a16260"},{"name":"2017-12-29_RE7_-_I.C.P._[1700].mp4","filesize":1483226378,"file_ext":"mp4","md5":"f86c1ca9b5b4bac95a6b6faacd199cc7"}]}}],"page":1,"per_page":999,"total_pages":1,"total_results":49}
