{"data": [{"id": 26600, "type": "episode", "attributes": {"title": "Rage Pals - Mario Odyssey - Darker Side!", "slug": "play-pals-2018-rage-pals-mario-odyssey-darker-side", "rating": null, "caption": "Deep within the moon, past a pool party, lies a dark heart of molten lava, gold, and rainbow colored spikes of pure evil. Michael, with his guide Gavin, dives into dispair. Will he emerge a changed man? Will he emerge at all?", "number": 1, "description": "Deep within the moon, past a pool party, lies a dark heart of molten lava, gold, and rainbow colored spikes of pure evil. Michael, with his guide Gavin, dives into dispair. Will he emerge a changed man? Will he emerge at all?", "display_title": "Rage Pals - Mario Odyssey - Darker Side!", "length": 2095, "advert_config": "", "advertising": true, "ad_timestamps": "0.00,523.75,1047.50,1571.25", "public_golive_at": "2018-04-24T17:00:00.000Z", "sponsor_golive_at": "2018-04-23T17:00:00.000Z", "member_golive_at": "2018-04-24T17:00:00.000Z", "original_air_date": "2018-04-23T17:00:00.000Z", "channel_id": "2cb2a70c-be50-46f5-93d7-84a1baabb4f7", "channel_slug": "achievement-hunter", "season_id": "9ecec38a-8210-4f38-a4c1-5601990ab8b6", "season_slug": "play-pals-2018", "season_number": 5, "show_title": "Play Pals", "show_id": "ff92a6d1-464d-11e7-a302-065410f210c4", "show_slug": "play-pals", "is_sponsors_only": false, "member_tier_i": -1, "sort_number": 50001, "genres": ["Gaming"], "is_live": true, "is_schedulable": true, "season_order": "desc", "episode_order": "desc", "downloadable": true, "blacklisted_countries": [], "upsell_next": false, "trending_score": 1.0, "time_boost": 18.042317, "credits_start_at": null, "trending_carousel": null}, "uuid": "0b61384c-5550-4ea2-a1a7-8e40176ecd47", "canonical_links": {"self": "/watch/play-pals-2018-rage-pals-mario-odyssey-darker-side", "show": "/series/play-pals"}, "archive": {"id": "roosterteeth-26600", "status": "archived", "files": [{"name": "2018-04-23_Rage_Pals_-_Mario_Odyssey_-_Darker_Side_[26600].description", "filesize": 225, "file_ext": "description", "md5": "2c530f40fb58331d3c634dba4250f8f8"}, {"name": "2018-04-23_Rage_Pals_-_Mario_Odyssey_-_Darker_Side_[26600].info.json", "filesize": 19852, "file_ext": "json", "md5": "970dfb8732a228d40d9dab58f780b2ac"}, {"name": "2018-04-23_Rage_Pals_-_Mario_Odyssey_-_Darker_Side_[26600].jpg", "filesize": 252877, "file_ext": "jpg", "md5": "d779dccec2e0de1f7a70efee8f5b1d4b"}, {"name": "2018-04-23_Rage_Pals_-_Mario_Odyssey_-_Darker_Side_[26600].mp4", "filesize": 1094833164, "file_ext": "mp4", "md5": "7448708b64499467d7734001014282e9"}]}}, {"id": 26788, "type": "episode", "attributes": {"title": "Call of Duty: Black Ops III", "slug": "play-pals-2018-call-of-duty-black-ops-iii", "rating": null, "caption": "Michael and special guest, James Buckley are the Play Mates. Using advanced technology like bow and arrows, they must destroy and mute their competition.", "number": 2, "description": "Michael and special guest, James Buckley are the Play Mates. Using advanced technology like bow and arrows, they must destroy and mute their competition.", "display_title": "Call of Duty: Black Ops III", "length": 1204, "advert_config": "", "advertising": true, "ad_timestamps": "0.00,401.33,802.67", "public_golive_at": "2018-05-08T17:00:00.000Z", "sponsor_golive_at": "2018-05-07T17:00:00.000Z", "member_golive_at": "2018-05-08T17:00:00.000Z", "original_air_date": "2018-05-07T17:00:00.000Z", "channel_id": "2cb2a70c-be50-46f5-93d7-84a1baabb4f7", "channel_slug": "achievement-hunter", "season_id": "9ecec38a-8210-4f38-a4c1-5601990ab8b6", "season_slug": "play-pals-2018", "season_number": 5, "show_title": "Play Pals", "show_id": "ff92a6d1-464d-11e7-a302-065410f210c4", "show_slug": "play-pals", "is_sponsors_only": false, "member_tier_i": -1, "sort_number": 50002, "genres": ["Gaming"], "is_live": true, "is_schedulable": true, "season_order": "desc", "episode_order": "desc", "downloadable": true, "blacklisted_countries": [], "upsell_next": false, "trending_score": 1.0, "time_boost": 18.050717, "credits_start_at": null, "trending_carousel": null}, "uuid": "e97928bd-09bb-47bc-8e00-c64e7c710703", "canonical_links": {"self": "/watch/play-pals-2018-call-of-duty-black-ops-iii", "show": "/series/play-pals"}, "archive": {"id": "roosterteeth-26788", "status": "archived", "files": [{"name": "2018-05-07_Call_of_Duty_Black_Ops_III_[26788].description", "filesize": 153, "file_ext": "description", "md5": "f2298c5ade64a30b68b81bace308851c"}, {"name": "2018-05-07_Call_of_Duty_Black_Ops_III_[26788].info.json", "filesize": 19714, "file_ext": "json", "md5": "21af37c68368c214e005c8051a9c6d5a"}, {"name": "2018-05-07_Call_of_Duty_Black_Ops_III_[26788].mp4", "filesize": 584521168, "file_ext": "mp4", "md5": "fe75fdd336e11cc70a17d78e59e99ad8"}, {"name": "2018-05-07_Call_of_Duty_Black_Ops_III_[26788].png", "filesize": 216299, "file_ext": "png", "md5": "7624e12f77e6255da3c98dc9afa713fd"}]}}, {"id": 27115, "type": "episode", "attributes": {"title": "Gavin Quits the Video - Play Pals - Emily Wants to Play Too", "slug": "play-pals-2018-mama-s-coming-for-you-play-pals-emily-wants-to-play-too", "rating": null, "caption": "Gavin and Michael Play Pals it up with Emily Wants to Play Too. There might be a jump scare or two. Or ten.", "number": 3, "description": "Gavin and Michael Play Pals it up with Emily Wants to Play Too. There might be a jump scare or two. Or ten.", "display_title": "Gavin Quits the Video - Play Pals - Emily Wants to Play Too", "length": 1897, "advert_config": "", "advertising": true, "ad_timestamps": "0.00,474.25,948.50,1422.75", "public_golive_at": "2018-06-05T17:00:00.000Z", "sponsor_golive_at": "2018-06-04T17:00:00.000Z", "member_golive_at": "2018-06-05T17:00:00.000Z", "original_air_date": "2018-06-04T17:00:00.000Z", "channel_id": "2cb2a70c-be50-46f5-93d7-84a1baabb4f7", "channel_slug": "achievement-hunter", "season_id": "9ecec38a-8210-4f38-a4c1-5601990ab8b6", "season_slug": "play-pals-2018", "season_number": 5, "show_title": "Play Pals", "show_id": "ff92a6d1-464d-11e7-a302-065410f210c4", "show_slug": "play-pals", "is_sponsors_only": false, "member_tier_i": -1, "sort_number": 50003, "genres": ["Gaming"], "is_live": true, "is_schedulable": true, "season_order": "desc", "episode_order": "desc", "downloadable": true, "blacklisted_countries": [], "upsell_next": false, "trending_score": 1.0, "time_boost": 18.060417, "credits_start_at": null, "trending_carousel": null}, "uuid": "0c7de0ac-4e4c-47dc-b0e3-819460b76e1d", "canonical_links": {"self": "/watch/play-pals-2018-mama-s-coming-for-you-play-pals-emily-wants-to-play-too", "show": "/series/play-pals"}, "archive": {"id": "roosterteeth-27115", "status": "archived", "files": [{"name": "2018-06-04_Gavin_Quits_the_Video_-_Play_Pals_-_Emily_Wants_to_Play_Too_[27115].description", "filesize": 107, "file_ext": "description", "md5": "367230d13c7047e1c6635bb3aa815de1"}, {"name": "2018-06-04_Gavin_Quits_the_Video_-_Play_Pals_-_Emily_Wants_to_Play_Too_[27115].info.json", "filesize": 19915, "file_ext": "json", "md5": "480814c7a7aedbe461417f5d095adacf"}, {"name": "2018-06-04_Gavin_Quits_the_Video_-_Play_Pals_-_Emily_Wants_to_Play_Too_[27115].jpg", "filesize": 213644, "file_ext": "jpg", "md5": "58f795c6de5b955ec73b773b582519a5"}, {"name": "2018-06-04_Gavin_Quits_the_Video_-_Play_Pals_-_Emily_Wants_to_Play_Too_[27115].mp4", "filesize": 969042500, "file_ext": "mp4", "md5": "99c4b4b6983ea7861def606c338c21c7"}]}}, {"id": 27475, "type": "episode", "attributes": {"title": "Hiccups and Holdy-Rolls - Super Bunny Man", "slug": "play-pals-2018-super-bunny-man", "rating": null, "caption": "Michael and Gavin must roll, hop, and grab there way through Super Bunny Man. Hopefully they won't get too distracted by all the carrots...", "number": 4, "description": "Michael and Gavin must roll, hop, and grab there way through Super Bunny Man. Hopefully they won't get too distracted by all the carrots...", "display_title": "Hiccups and Holdy-Rolls - Super Bunny Man", "length": 1973, "advert_config": "", "advertising": true, "ad_timestamps": "1615.00,370.00,795.00,1210.00", "public_golive_at": "2018-06-19T17:00:00.000Z", "sponsor_golive_at": "2018-06-18T17:00:00.000Z", "member_golive_at": "2018-06-19T17:00:00.000Z", "original_air_date": "2018-06-18T17:00:00.000Z", "channel_id": "2cb2a70c-be50-46f5-93d7-84a1baabb4f7", "channel_slug": "achievement-hunter", "season_id": "9ecec38a-8210-4f38-a4c1-5601990ab8b6", "season_slug": "play-pals-2018", "season_number": 5, "show_title": "Play Pals", "show_id": "ff92a6d1-464d-11e7-a302-065410f210c4", "show_slug": "play-pals", "is_sponsors_only": false, "member_tier_i": -1, "sort_number": 50004, "genres": ["Gaming"], "is_live": true, "is_schedulable": true, "season_order": "desc", "episode_order": "desc", "downloadable": true, "blacklisted_countries": [], "upsell_next": false, "trending_score": 1.0, "time_boost": 18.061817, "credits_start_at": null, "trending_carousel": false}, "uuid": "f6d557a1-ca13-4eff-b45c-fe82f4742e42", "canonical_links": {"self": "/watch/play-pals-2018-super-bunny-man", "show": "/series/play-pals"}, "archive": {"id": "roosterteeth-27475", "status": "archived", "files": [{"name": "2018-06-18_Hiccups_and_Holdy-Rolls_-_Super_Bunny_Man_[27475].description", "filesize": 139, "file_ext": "description", "md5": "a6a7a726ca9e6416be0d370d2129a9bc"}, {"name": "2018-06-18_Hiccups_and_Holdy-Rolls_-_Super_Bunny_Man_[27475].info.json", "filesize": 19798, "file_ext": "json", "md5": "0e16738cfe7544149a8b6741eb5ca2fe"}, {"name": "2018-06-18_Hiccups_and_Holdy-Rolls_-_Super_Bunny_Man_[27475].jpg", "filesize": 138139, "file_ext": "jpg", "md5": "a29160efddca19fad9046810e78c4b15"}, {"name": "2018-06-18_Hiccups_and_Holdy-Rolls_-_Super_Bunny_Man_[27475].mp4", "filesize": 1036031984, "file_ext": "mp4", "md5": "32c04aefdf9fbf56ee40570b0d88d56d"}]}}, {"id": 27639, "type": "episode", "attributes": {"title": "The Actual Game This Time - Emily Wants to Play Too", "slug": "play-pals-2018-the-actual-game-this-time-emily-wants-to-play-too", "rating": null, "caption": "Michael and Gavin finish the tutorial and are ready to play the real meat of Emily Wants to Play Too. Even when they're prepared for all the jump scares, they're not prepared for all the jump scares.", "number": 5, "description": "Michael and Gavin finish the tutorial and are ready to play the real meat of Emily Wants to Play Too. Even when they're prepared for all the jump scares, they're not prepared for all the jump scares.", "display_title": "The Actual Game This Time - Emily Wants to Play Too", "length": 2817, "advert_config": "", "advertising": true, "ad_timestamps": "1060.00,1442.00,1867.00,2325.00,230.00,616.00", "public_golive_at": "2018-07-03T17:00:00.000Z", "sponsor_golive_at": "2018-07-02T17:00:00.000Z", "member_golive_at": "2018-07-03T17:00:00.000Z", "original_air_date": "2018-07-02T17:00:00.000Z", "channel_id": "2cb2a70c-be50-46f5-93d7-84a1baabb4f7", "channel_slug": "achievement-hunter", "season_id": "9ecec38a-8210-4f38-a4c1-5601990ab8b6", "season_slug": "play-pals-2018", "season_number": 5, "show_title": "Play Pals", "show_id": "ff92a6d1-464d-11e7-a302-065410f210c4", "show_slug": "play-pals", "is_sponsors_only": false, "member_tier_i": -1, "sort_number": 50005, "genres": ["Gaming"], "is_live": true, "is_schedulable": true, "season_order": "desc", "episode_order": "desc", "downloadable": true, "blacklisted_countries": [], "upsell_next": false, "trending_score": 1.0, "time_boost": 18.070217, "credits_start_at": null, "trending_carousel": null}, "uuid": "a02b53aa-48e6-4b0a-a21e-867da2914def", "canonical_links": {"self": "/watch/play-pals-2018-the-actual-game-this-time-emily-wants-to-play-too", "show": "/series/play-pals"}, "archive": {"id": "roosterteeth-27639", "status": "archived", "files": [{"name": "2018-07-02_The_Actual_Game_This_Time_-_Emily_Wants_to_Play_Too_[27639].description", "filesize": 199, "file_ext": "description", "md5": "9861ff795d637210008ab15fb6a67df7"}, {"name": "2018-07-02_The_Actual_Game_This_Time_-_Emily_Wants_to_Play_Too_[27639].info.json", "filesize": 19975, "file_ext": "json", "md5": "c1ca1e3da283b38bf1f81cbb988aa8f2"}, {"name": "2018-07-02_The_Actual_Game_This_Time_-_Emily_Wants_to_Play_Too_[27639].jpg", "filesize": 260117, "file_ext": "jpg", "md5": "9bb491da2aa42b4ebd1617f58077f25e"}, {"name": "2018-07-02_The_Actual_Game_This_Time_-_Emily_Wants_to_Play_Too_[27639].mp4", "filesize": 1463437871, "file_ext": "mp4", "md5": "d127f994fd79e1c97e16a9841d235b21"}]}}, {"id": 27883, "type": "episode", "attributes": {"title": "I'll Save You! - Play Pals - Super Bunny Man (#2)", "slug": "play-pals-2018-super-bunny-man-2", "rating": null, "caption": "The Play Pals are hippin and hoppin again in Super Bunny Man. New music theme, new world, and there's even an attempt at a speedrun for a couple levels. Don't worry, there's still plenty of screaming.", "number": 6, "description": "The Play Pals are hippin and hoppin again in Super Bunny Man. New music theme, new world, and there's even an attempt at a speedrun for a couple levels. Don't worry, there's still plenty of screaming.", "display_title": "I'll Save You! - Play Pals - Super Bunny Man (#2)", "length": 2901, "advert_config": "", "advertising": true, "ad_timestamps": "1563.00,1955.00,2407.00,385.00,780.00,1176.00", "public_golive_at": "2018-07-17T17:00:00.000Z", "sponsor_golive_at": "2018-07-16T17:00:00.000Z", "member_golive_at": "2018-07-17T17:00:00.000Z", "original_air_date": "2018-07-16T17:00:00.000Z", "channel_id": "2cb2a70c-be50-46f5-93d7-84a1baabb4f7", "channel_slug": "achievement-hunter", "season_id": "9ecec38a-8210-4f38-a4c1-5601990ab8b6", "season_slug": "play-pals-2018", "season_number": 5, "show_title": "Play Pals", "show_id": "ff92a6d1-464d-11e7-a302-065410f210c4", "show_slug": "play-pals", "is_sponsors_only": false, "member_tier_i": -1, "sort_number": 50006, "genres": ["Gaming"], "is_live": true, "is_schedulable": true, "season_order": "desc", "episode_order": "desc", "downloadable": true, "blacklisted_countries": [], "upsell_next": false, "trending_score": 1.0, "time_boost": 18.071617, "credits_start_at": null, "trending_carousel": false}, "uuid": "38f5d28a-1e09-4482-b73e-230a9b38707e", "canonical_links": {"self": "/watch/play-pals-2018-super-bunny-man-2", "show": "/series/play-pals"}, "archive": {"id": "roosterteeth-27883", "status": "archived", "files": [{"name": "2018-07-16_Ill_Save_You_-_Play_Pals_-_Super_Bunny_Man_2_[27883].description", "filesize": 200, "file_ext": "description", "md5": "fcdf66b1ceca50c3ac776a8a88e4bc97"}, {"name": "2018-07-16_Ill_Save_You_-_Play_Pals_-_Super_Bunny_Man_2_[27883].info.json", "filesize": 19834, "file_ext": "json", "md5": "41214110ed882e343da643a362e3cf65"}, {"name": "2018-07-16_Ill_Save_You_-_Play_Pals_-_Super_Bunny_Man_2_[27883].jpg", "filesize": 76004, "file_ext": "jpg", "md5": "5bcb3ca0d2784da6f8a05fddcb49a1ec"}, {"name": "2018-07-16_Ill_Save_You_-_Play_Pals_-_Super_Bunny_Man_2_[27883].mp4", "filesize": 1519636848, "file_ext": "mp4", "md5": "1ec0264582b68d53b0a7180cb64398c8"}]}}, {"id": 28050, "type": "episode", "attributes": {"title": "Little Yarny Boys  - Unravel Two", "slug": "play-pals-2018-little-yarny-boys-unravel-two", "rating": null, "caption": "Join the Play Pals as they throw yarn, tie yarn, and even climb yarn to solve the puzzles Unravel Two has to offer!", "number": 7, "description": "Join the Play Pals as they throw yarn, tie yarn, and even climb yarn to solve the puzzles Unravel Two has to offer!", "display_title": "Little Yarny Boys  - Unravel Two", "length": 3306, "advert_config": "", "advertising": true, "ad_timestamps": "1942.00,2336.00,2790.00,301.00,728.00,1095.00,1488.00", "public_golive_at": "2018-07-31T17:00:00.000Z", "sponsor_golive_at": "2018-07-30T17:00:00.000Z", "member_golive_at": "2018-07-31T17:00:00.000Z", "original_air_date": "2018-07-30T17:00:00.000Z", "channel_id": "2cb2a70c-be50-46f5-93d7-84a1baabb4f7", "channel_slug": "achievement-hunter", "season_id": "9ecec38a-8210-4f38-a4c1-5601990ab8b6", "season_slug": "play-pals-2018", "season_number": 5, "show_title": "Play Pals", "show_id": "ff92a6d1-464d-11e7-a302-065410f210c4", "show_slug": "play-pals", "is_sponsors_only": false, "member_tier_i": -1, "sort_number": 50007, "genres": ["Gaming"], "is_live": true, "is_schedulable": true, "season_order": "desc", "episode_order": "desc", "downloadable": true, "blacklisted_countries": [], "upsell_next": false, "trending_score": 1.0, "time_boost": 18.073017, "credits_start_at": null, "trending_carousel": null}, "uuid": "261ad625-defc-4c78-8161-a121b570d9c2", "canonical_links": {"self": "/watch/play-pals-2018-little-yarny-boys-unravel-two", "show": "/series/play-pals"}, "archive": {"id": "roosterteeth-28050", "status": "archived", "files": [{"name": "2018-07-30_Little_Yarny_Boys__-_Unravel_Two_[28050].description", "filesize": 115, "file_ext": "description", "md5": "20702e26459d555438ac3a79a084bb1f"}, {"name": "2018-07-30_Little_Yarny_Boys__-_Unravel_Two_[28050].info.json", "filesize": 19700, "file_ext": "json", "md5": "361618596f8e4196abc27b4077921550"}, {"name": "2018-07-30_Little_Yarny_Boys__-_Unravel_Two_[28050].jpg", "filesize": 258583, "file_ext": "jpg", "md5": "d9ed489659ff246bb3ad36d0042a0cee"}, {"name": "2018-07-30_Little_Yarny_Boys__-_Unravel_Two_[28050].mp4", "filesize": 1745479135, "file_ext": "mp4", "md5": "cd29058f63a1060c802f48a6b148f117"}]}}, {"id": 28220, "type": "episode", "attributes": {"title": "Sucking Carrot - Super Bunny Man (#3)", "slug": "play-pals-2018-super-bunny-man-3", "rating": null, "caption": "One in the cart, and the other needs a head start. The Play Pals are back in Super Bunny Man! After a speedrun warm-up, they dive into world #3, the Deep Caves.", "number": 8, "description": "One in the cart, and the other needs a head start. The Play Pals are back in Super Bunny Man! After a speedrun warm-up, they dive into world #3, the Deep Caves.", "display_title": "Sucking Carrot - Super Bunny Man (#3)", "length": 2844, "advert_config": "", "advertising": true, "ad_timestamps": "807.00,1244.00,1647.00,2082.00,2490.00,434.00", "public_golive_at": "2018-08-14T17:00:00.000Z", "sponsor_golive_at": "2018-08-13T17:00:00.000Z", "member_golive_at": "2018-08-14T17:00:00.000Z", "original_air_date": "2018-08-13T17:00:00.000Z", "channel_id": "2cb2a70c-be50-46f5-93d7-84a1baabb4f7", "channel_slug": "achievement-hunter", "season_id": "9ecec38a-8210-4f38-a4c1-5601990ab8b6", "season_slug": "play-pals-2018", "season_number": 5, "show_title": "Play Pals", "show_id": "ff92a6d1-464d-11e7-a302-065410f210c4", "show_slug": "play-pals", "is_sponsors_only": false, "member_tier_i": -1, "sort_number": 50008, "genres": ["Gaming"], "is_live": true, "is_schedulable": true, "season_order": "desc", "episode_order": "desc", "downloadable": true, "blacklisted_countries": [], "upsell_next": false, "trending_score": 1.0, "time_boost": 18.081317, "credits_start_at": null, "trending_carousel": null}, "uuid": "da6ba33b-341d-4e72-a5e7-2127c089b7a5", "canonical_links": {"self": "/watch/play-pals-2018-super-bunny-man-3", "show": "/series/play-pals"}, "archive": {"id": "roosterteeth-28220", "status": "archived", "files": [{"name": "2018-08-13_Sucking_Carrot_-_Super_Bunny_Man_3_[28220].description", "filesize": 160, "file_ext": "description", "md5": "85b50ac6c94fc5be9b8d0c1b4a3730d7"}, {"name": "2018-08-13_Sucking_Carrot_-_Super_Bunny_Man_3_[28220].info.json", "filesize": 19848, "file_ext": "json", "md5": "6a89bf89be5999e4c2a6f8d40eef9fed"}, {"name": "2018-08-13_Sucking_Carrot_-_Super_Bunny_Man_3_[28220].jpg", "filesize": 154530, "file_ext": "jpg", "md5": "a08e9fe4c3430568c87a950eee49252f"}, {"name": "2018-08-13_Sucking_Carrot_-_Super_Bunny_Man_3_[28220].mp4", "filesize": 1488380486, "file_ext": "mp4", "md5": "3ea8d81d3432e9155c858bbce17c8fdb"}]}}, {"id": 28383, "type": "episode", "attributes": {"title": "Getting Hospitalized - Helping Hand", "slug": "play-pals-2018-getting-hospitalized-helping-hand", "rating": null, "caption": "The boys take a break from Super Bunny Man and give Helping Hand a whirl. And oh man do they definitely play Helping Hand.", "number": 9, "description": "The boys take a break from Super Bunny Man and give Helping Hand a whirl. And oh man do they definitely play Helping Hand. They play that game so hard. If there's one thing you'll say after watching this video, it's that they played the video game Helping Hand.", "display_title": "Getting Hospitalized - Helping Hand", "length": 1623, "advert_config": "", "advertising": true, "ad_timestamps": "389.27,792.32,1181.31", "public_golive_at": "2018-08-28T17:00:00.000Z", "sponsor_golive_at": "2018-08-27T17:00:00.000Z", "member_golive_at": "2018-08-28T17:00:00.000Z", "original_air_date": "2018-08-27T17:00:00.000Z", "channel_id": "2cb2a70c-be50-46f5-93d7-84a1baabb4f7", "channel_slug": "achievement-hunter", "season_id": "9ecec38a-8210-4f38-a4c1-5601990ab8b6", "season_slug": "play-pals-2018", "season_number": 5, "show_title": "Play Pals", "show_id": "ff92a6d1-464d-11e7-a302-065410f210c4", "show_slug": "play-pals", "is_sponsors_only": false, "member_tier_i": -1, "sort_number": 50009, "genres": ["Gaming"], "is_live": true, "is_schedulable": true, "season_order": "desc", "episode_order": "desc", "downloadable": true, "blacklisted_countries": [], "upsell_next": false, "trending_score": 1.0, "time_boost": 18.082717, "credits_start_at": null, "trending_carousel": null}, "uuid": "0d7bb110-31b3-4686-9d99-1938b7eb5146", "canonical_links": {"self": "/watch/play-pals-2018-getting-hospitalized-helping-hand", "show": "/series/play-pals"}, "archive": {"id": "roosterteeth-28383", "status": "archived", "files": [{"name": "2018-08-27_Getting_Hospitalized_-_Helping_Hand_[28383].description", "filesize": 261, "file_ext": "description", "md5": "c7b83ab5cd36633094ff3f7b29e5d656"}, {"name": "2018-08-27_Getting_Hospitalized_-_Helping_Hand_[28383].info.json", "filesize": 19941, "file_ext": "json", "md5": "67bf6e8452527fbd5ed1932c2d63935a"}, {"name": "2018-08-27_Getting_Hospitalized_-_Helping_Hand_[28383].jpg", "filesize": 153256, "file_ext": "jpg", "md5": "38f9d7eeddd292ec6b35784077ecf678"}, {"name": "2018-08-27_Getting_Hospitalized_-_Helping_Hand_[28383].mp4", "filesize": 857133814, "file_ext": "mp4", "md5": "9581e34a26b1b9fe39cd3f1d4127898b"}]}}, {"id": 28542, "type": "episode", "attributes": {"title": "Burping Through the Tears - Super Bunny Man (#4)", "slug": "play-pals-2018-burping-through-the-tears-super-bunny-man-4", "rating": null, "caption": "The Pals continue their descent into World #3, the Deep Caves. And while progress is made, Gavin falls to pieces and Michael is brought to tears.", "number": 10, "description": "The Pals continue their descent into World #3, the Deep Caves. And while progress is made, Gavin falls to pieces and Michael is brought to tears.", "display_title": "Burping Through the Tears - Super Bunny Man (#4)", "length": 2483, "advert_config": "", "advertising": true, "ad_timestamps": "413.13,835.30,1249.37,1636.51,2062.50", "public_golive_at": "2018-09-11T17:00:00.000Z", "sponsor_golive_at": "2018-09-10T17:00:00.000Z", "member_golive_at": "2018-09-11T17:00:00.000Z", "original_air_date": "2018-09-10T17:00:00.000Z", "channel_id": "2cb2a70c-be50-46f5-93d7-84a1baabb4f7", "channel_slug": "achievement-hunter", "season_id": "9ecec38a-8210-4f38-a4c1-5601990ab8b6", "season_slug": "play-pals-2018", "season_number": 5, "show_title": "Play Pals", "show_id": "ff92a6d1-464d-11e7-a302-065410f210c4", "show_slug": "play-pals", "is_sponsors_only": false, "member_tier_i": -1, "sort_number": 50010, "genres": ["Gaming"], "is_live": true, "is_schedulable": true, "season_order": "desc", "episode_order": "desc", "downloadable": true, "blacklisted_countries": [], "upsell_next": false, "trending_score": 1.0, "time_boost": 18.091017, "credits_start_at": null, "trending_carousel": null}, "uuid": "c5136c33-ea2e-4324-ab16-5aeb0524dab1", "canonical_links": {"self": "/watch/play-pals-2018-burping-through-the-tears-super-bunny-man-4", "show": "/series/play-pals"}, "archive": {"id": "roosterteeth-28542", "status": "archived", "files": [{"name": "2018-09-10_Burping_Through_the_Tears_-_Super_Bunny_Man_4_[28542].description", "filesize": 145, "file_ext": "description", "md5": "49dcd64a0a5ae1bad7a6219480759e3e"}, {"name": "2018-09-10_Burping_Through_the_Tears_-_Super_Bunny_Man_4_[28542].info.json", "filesize": 19945, "file_ext": "json", "md5": "2c9256df73eb96ec425a52e7d24bae1c"}, {"name": "2018-09-10_Burping_Through_the_Tears_-_Super_Bunny_Man_4_[28542].jpg", "filesize": 156183, "file_ext": "jpg", "md5": "065ccd3c73e6bcd0a313e7d7abe80efa"}, {"name": "2018-09-10_Burping_Through_the_Tears_-_Super_Bunny_Man_4_[28542].mp4", "filesize": 1303961888, "file_ext": "mp4", "md5": "cdcf74655541a133db46244a019201ac"}]}}, {"id": 28807, "type": "episode", "attributes": {"title": "Not An Ideal Situation - Super Bunny Man (#5)", "slug": "play-pals-2018-not-an-ideal-situation-super-bunny-man-5", "rating": null, "caption": "Deeper still into the Deep Caves of Super Bunny Man! This one ain't exactly a speedrun. Minecarts and spikes of all types keep the bunny men from hopping, but that ain't stopping them!", "number": 11, "description": "Deeper still into the Deep Caves of Super Bunny Man! This one ain't exactly a speedrun. Minecarts and spikes of all types keep the bunny men from hopping, but that ain't stopping them!", "display_title": "Not An Ideal Situation - Super Bunny Man (#5)", "length": 3058, "advert_config": "", "advertising": true, "ad_timestamps": "302.09,736.03,1155.55,1678.41,2162.52,2641.34", "public_golive_at": "2018-10-02T17:00:00.000Z", "sponsor_golive_at": "2018-10-01T17:00:00.000Z", "member_golive_at": "2018-10-02T17:00:00.000Z", "original_air_date": "2018-10-01T17:00:00.000Z", "channel_id": "2cb2a70c-be50-46f5-93d7-84a1baabb4f7", "channel_slug": "achievement-hunter", "season_id": "9ecec38a-8210-4f38-a4c1-5601990ab8b6", "season_slug": "play-pals-2018", "season_number": 5, "show_title": "Play Pals", "show_id": "ff92a6d1-464d-11e7-a302-065410f210c4", "show_slug": "play-pals", "is_sponsors_only": false, "member_tier_i": -1, "sort_number": 50011, "genres": ["Gaming"], "is_live": true, "is_schedulable": true, "season_order": "desc", "episode_order": "desc", "downloadable": true, "blacklisted_countries": [], "upsell_next": false, "trending_score": 1.0, "time_boost": 18.100117, "credits_start_at": null, "trending_carousel": null}, "uuid": "cd5be35e-f00e-46d7-8dff-51e39b8671f6", "canonical_links": {"self": "/watch/play-pals-2018-not-an-ideal-situation-super-bunny-man-5", "show": "/series/play-pals"}, "archive": {"id": "roosterteeth-28807", "status": "archived", "files": [{"name": "2018-10-01_Not_An_Ideal_Situation_-_Super_Bunny_Man_5_[28807].description", "filesize": 184, "file_ext": "description", "md5": "a7ae4f5f63dc40920b2278baf39bade3"}, {"name": "2018-10-01_Not_An_Ideal_Situation_-_Super_Bunny_Man_5_[28807].info.json", "filesize": 19916, "file_ext": "json", "md5": "08aa491b2f507377dd132050ae1edbcc"}, {"name": "2018-10-01_Not_An_Ideal_Situation_-_Super_Bunny_Man_5_[28807].jpg", "filesize": 142551, "file_ext": "jpg", "md5": "2b1448ea872bc5fc1945a4eb35787dd3"}, {"name": "2018-10-01_Not_An_Ideal_Situation_-_Super_Bunny_Man_5_[28807].mp4", "filesize": 1606630731, "file_ext": "mp4", "md5": "778e2410ce3cc863fc9f3b2c65c84559"}]}}, {"id": 28889, "type": "episode", "attributes": {"title": "A Couple of Miners - Super Bunny Man (#6)", "slug": "play-pals-2018-a-couple-of-miners-super-bunny-man-6", "rating": null, "caption": "The Play Pals are still stuck in the mines in Super Bunny Man. As the clock ticks down to Gavin's meeting, can the Play Pals escape the caves, or will Michael be left on his own?", "number": 12, "description": "The Play Pals are still stuck in the mines in Super Bunny Man. As the clock ticks down to Gavin's meeting, can the Play Pals escape the caves, or will Michael be left on his own?", "display_title": "A Couple of Miners - Super Bunny Man (#6)", "length": 2854, "advert_config": "", "advertising": true, "ad_timestamps": "335.02,709.28,1112.13,1791.34,2250.40", "public_golive_at": "2018-10-09T17:00:00.000Z", "sponsor_golive_at": "2018-10-08T17:00:00.000Z", "member_golive_at": "2018-10-09T17:00:00.000Z", "original_air_date": "2018-10-08T17:00:00.000Z", "channel_id": "2cb2a70c-be50-46f5-93d7-84a1baabb4f7", "channel_slug": "achievement-hunter", "season_id": "9ecec38a-8210-4f38-a4c1-5601990ab8b6", "season_slug": "play-pals-2018", "season_number": 5, "show_title": "Play Pals", "show_id": "ff92a6d1-464d-11e7-a302-065410f210c4", "show_slug": "play-pals", "is_sponsors_only": false, "member_tier_i": -1, "sort_number": 50012, "genres": ["Gaming"], "is_live": true, "is_schedulable": true, "season_order": "desc", "episode_order": "desc", "downloadable": true, "blacklisted_countries": [], "upsell_next": false, "trending_score": 1.0, "time_boost": 18.100817, "credits_start_at": null, "trending_carousel": null}, "uuid": "38d3060b-7b82-4da6-ac4a-32f208c6bbdc", "canonical_links": {"self": "/watch/play-pals-2018-a-couple-of-miners-super-bunny-man-6", "show": "/series/play-pals"}, "archive": {"id": "roosterteeth-28889", "status": "archived", "files": [{"name": "2018-10-08_A_Couple_of_Miners_-_Super_Bunny_Man_6_[28889].description", "filesize": 178, "file_ext": "description", "md5": "c0171589103c70d31bcb3e0b6a0f4318"}, {"name": "2018-10-08_A_Couple_of_Miners_-_Super_Bunny_Man_6_[28889].info.json", "filesize": 19837, "file_ext": "json", "md5": "4494271d88c4531f2ee341d2b2d13901"}, {"name": "2018-10-08_A_Couple_of_Miners_-_Super_Bunny_Man_6_[28889].mp4", "filesize": 1490609666, "file_ext": "mp4", "md5": "58da04f4b2e2b45aefa6e6918e3d1698"}, {"name": "2018-10-08_A_Couple_of_Miners_-_Super_Bunny_Man_6_[28889].png", "filesize": 184693, "file_ext": "png", "md5": "1e12bc7ff29866d91f4f64a0455ea2c9"}]}}, {"id": 29047, "type": "episode", "attributes": {"title": "Summer Bois - Super Bunny Man (#7)", "slug": "play-pals-2018-summer-bois-super-bunny-man-7", "rating": null, "caption": "Time to find out if bunnies can swim! The Pals start the last available world of Super Bunny Man, Sandy Beach. Get ready for some wet stunts!", "number": 13, "description": "Time to find out if bunnies can swim! The Pals start the last available world of Super Bunny Man, Sandy Beach. Get ready for some wet stunts!", "display_title": "Summer Bois - Super Bunny Man (#7)", "length": 1961, "advert_config": "", "advertising": true, "ad_timestamps": "387.51,768.30,1181.36,1547.03", "public_golive_at": "2018-10-23T17:00:00.000Z", "sponsor_golive_at": "2018-10-22T17:00:00.000Z", "member_golive_at": "2018-10-23T17:00:00.000Z", "original_air_date": "2018-10-22T17:00:00.000Z", "channel_id": "2cb2a70c-be50-46f5-93d7-84a1baabb4f7", "channel_slug": "achievement-hunter", "season_id": "9ecec38a-8210-4f38-a4c1-5601990ab8b6", "season_slug": "play-pals-2018", "season_number": 5, "show_title": "Play Pals", "show_id": "ff92a6d1-464d-11e7-a302-065410f210c4", "show_slug": "play-pals", "is_sponsors_only": false, "member_tier_i": -1, "sort_number": 50013, "genres": ["Gaming"], "is_live": true, "is_schedulable": true, "season_order": "desc", "episode_order": "desc", "downloadable": true, "blacklisted_countries": [], "upsell_next": false, "trending_score": 1.0, "time_boost": 18.102217, "credits_start_at": null, "trending_carousel": null}, "uuid": "58ffe5b7-ce6d-481c-9de5-af0a98689cb6", "canonical_links": {"self": "/watch/play-pals-2018-summer-bois-super-bunny-man-7", "show": "/series/play-pals"}, "archive": {"id": "roosterteeth-29047", "status": "archived", "files": [{"name": "2018-10-22_Summer_Bois_-_Super_Bunny_Man_7_[29047].description", "filesize": 141, "file_ext": "description", "md5": "ab177c515bf0f1e6e202ca269f373a70"}, {"name": "2018-10-22_Summer_Bois_-_Super_Bunny_Man_7_[29047].info.json", "filesize": 19842, "file_ext": "json", "md5": "e40ccc4fa1ae62188d9a1313d2d032d3"}, {"name": "2018-10-22_Summer_Bois_-_Super_Bunny_Man_7_[29047].jpg", "filesize": 151246, "file_ext": "jpg", "md5": "4cfae0028407b85adef1ee18687dd5b8"}, {"name": "2018-10-22_Summer_Bois_-_Super_Bunny_Man_7_[29047].mp4", "filesize": 1034091072, "file_ext": "mp4", "md5": "aa477bac3bbf41623c1c4956f0db7b6a"}]}}, {"id": 29149, "type": "episode", "attributes": {"title": "Poop Pals - A Dump in the Dark", "slug": "play-pals-2018-dump-in-the-dark", "rating": null, "caption": "The Play Pals embark on a fright-filled journey of killer clowns, hungry babies, and sewer monsters. Did I mention that they're a butt that shoots shit at things?", "number": 14, "description": "WARNING, this game is fucking gross. Don't watch this if you are eating, or become squeamish easily.\r\nThe Play Pals embark on a fright-filled journey of killer clowns, hungry babies, and sewer monsters. Did I mention that they're a butt that shoots shit at things?", "display_title": "Poop Pals - A Dump in the Dark", "length": 2115, "advert_config": "", "advertising": true, "ad_timestamps": "507.22,877.50,1304.05,1615.46", "public_golive_at": "2018-10-31T19:00:00.000Z", "sponsor_golive_at": "2018-10-30T19:00:00.000Z", "member_golive_at": "2018-10-31T19:00:00.000Z", "original_air_date": "2018-10-30T19:00:00.000Z", "channel_id": "2cb2a70c-be50-46f5-93d7-84a1baabb4f7", "channel_slug": "achievement-hunter", "season_id": "9ecec38a-8210-4f38-a4c1-5601990ab8b6", "season_slug": "play-pals-2018", "season_number": 5, "show_title": "Play Pals", "show_id": "ff92a6d1-464d-11e7-a302-065410f210c4", "show_slug": "play-pals", "is_sponsors_only": false, "member_tier_i": -1, "sort_number": 50014, "genres": ["Gaming"], "is_live": true, "is_schedulable": true, "season_order": "desc", "episode_order": "desc", "downloadable": true, "blacklisted_countries": [], "upsell_next": false, "trending_score": 1.0, "time_boost": 18.103019, "credits_start_at": null, "trending_carousel": null}, "uuid": "91549e2e-99d1-4870-aecb-1ef953420ef5", "canonical_links": {"self": "/watch/play-pals-2018-dump-in-the-dark", "show": "/series/play-pals"}, "archive": {"id": "roosterteeth-29149", "status": "archived", "files": [{"name": "2018-10-30_Poop_Pals_-_A_Dump_in_the_Dark_[29149].description", "filesize": 264, "file_ext": "description", "md5": "8fc134ae2a9a4dc5a5a0e431cd64b63a"}, {"name": "2018-10-30_Poop_Pals_-_A_Dump_in_the_Dark_[29149].info.json", "filesize": 19851, "file_ext": "json", "md5": "c029b38a0b998a5793f2b61735dc053a"}, {"name": "2018-10-30_Poop_Pals_-_A_Dump_in_the_Dark_[29149].mp4", "filesize": 1108212010, "file_ext": "mp4", "md5": "92f7469c2827b262598c9d2e39cfc349"}, {"name": "2018-10-30_Poop_Pals_-_A_Dump_in_the_Dark_[29149].png", "filesize": 172672, "file_ext": "png", "md5": "83a8f8943323f7210d3fa17cb4bd6d77"}]}}, {"id": 29166, "type": "episode", "attributes": {"title": "Monkey Business - Dark Deception", "slug": "play-pals-2018-dark-deception", "rating": null, "caption": "Trapped in a hotel full of chilling secrets and razor sharp monkeys? Nothing the Play Pals can't handle.", "number": 15, "description": "Trapped in a hotel full of chilling secrets and razor sharp monkeys? Nothing the Play Pals can't handle.", "display_title": "Monkey Business - Dark Deception", "length": 2997, "advert_config": "", "advertising": true, "ad_timestamps": "567.57,826.14,1365.54,1773.15,2131.25,2865.01", "public_golive_at": "2018-10-30T17:00:00.000Z", "sponsor_golive_at": "2018-10-29T17:00:00.000Z", "member_golive_at": "2018-10-30T17:00:00.000Z", "original_air_date": "2018-10-29T17:00:00.000Z", "channel_id": "2cb2a70c-be50-46f5-93d7-84a1baabb4f7", "channel_slug": "achievement-hunter", "season_id": "9ecec38a-8210-4f38-a4c1-5601990ab8b6", "season_slug": "play-pals-2018", "season_number": 5, "show_title": "Play Pals", "show_id": "ff92a6d1-464d-11e7-a302-065410f210c4", "show_slug": "play-pals", "is_sponsors_only": false, "member_tier_i": -1, "sort_number": 50015, "genres": ["Gaming"], "is_live": true, "is_schedulable": true, "season_order": "desc", "episode_order": "desc", "downloadable": true, "blacklisted_countries": [], "upsell_next": false, "trending_score": 1.0, "time_boost": 18.102917, "credits_start_at": null, "trending_carousel": null}, "uuid": "5e8dd095-d294-4265-9ed7-05660c25e633", "canonical_links": {"self": "/watch/play-pals-2018-dark-deception", "show": "/series/play-pals"}, "archive": {"id": "roosterteeth-29166", "status": "archived", "files": [{"name": "2018-10-29_Monkey_Business_-_Dark_Deception_[29166].description", "filesize": 104, "file_ext": "description", "md5": "f9ac01cec1f043d273c6eb025fc74f45"}, {"name": "2018-10-29_Monkey_Business_-_Dark_Deception_[29166].info.json", "filesize": 19694, "file_ext": "json", "md5": "1dc6833b8505b6bc01b3bbe45b8de513"}, {"name": "2018-10-29_Monkey_Business_-_Dark_Deception_[29166].jpg", "filesize": 131939, "file_ext": "jpg", "md5": "6dd6bd8640c72a2e185131e79422cf73"}, {"name": "2018-10-29_Monkey_Business_-_Dark_Deception_[29166].mp4", "filesize": 1570604867, "file_ext": "mp4", "md5": "99ca62322943028aa2fc4496beebc036"}]}}, {"id": 29332, "type": "episode", "attributes": {"title": "Clipping Jugs - Super Bunny Man (#8)", "slug": "play-pals-2018-clipping-jugs-super-bunny-man-8", "rating": null, "caption": "The Pals are driven to hate eating by the unforgiving beaches of Super Bunny Man.", "number": 16, "description": "The Pals are driven to hate eating by the unforgiving beaches of Super Bunny Man.", "display_title": "Clipping Jugs - Super Bunny Man (#8)", "length": 2188, "advert_config": "", "advertising": true, "ad_timestamps": "436.28,843.15,1263.33,1685.17", "public_golive_at": "2018-11-13T18:00:00.000Z", "sponsor_golive_at": "2018-11-12T18:00:00.000Z", "member_golive_at": "2018-11-13T18:00:00.000Z", "original_air_date": "2018-11-12T18:00:00.000Z", "channel_id": "2cb2a70c-be50-46f5-93d7-84a1baabb4f7", "channel_slug": "achievement-hunter", "season_id": "9ecec38a-8210-4f38-a4c1-5601990ab8b6", "season_slug": "play-pals-2018", "season_number": 5, "show_title": "Play Pals", "show_id": "ff92a6d1-464d-11e7-a302-065410f210c4", "show_slug": "play-pals", "is_sponsors_only": false, "member_tier_i": -1, "sort_number": 50016, "genres": ["Gaming"], "is_live": true, "is_schedulable": true, "season_order": "desc", "episode_order": "desc", "downloadable": true, "blacklisted_countries": [], "upsell_next": false, "trending_score": 1.0, "time_boost": 18.111218, "credits_start_at": null, "trending_carousel": null}, "uuid": "352a3a1e-2c61-4bd8-9644-f799ce4a8985", "canonical_links": {"self": "/watch/play-pals-2018-clipping-jugs-super-bunny-man-8", "show": "/series/play-pals"}, "archive": {"id": "roosterteeth-29332", "status": "archived", "files": [{"name": "2018-11-12_Clipping_Jugs_-_Super_Bunny_Man_8_[29332].description", "filesize": 81, "file_ext": "description", "md5": "1e1982ac650028afa01c1b417387846a"}, {"name": "2018-11-12_Clipping_Jugs_-_Super_Bunny_Man_8_[29332].info.json", "filesize": 19794, "file_ext": "json", "md5": "39bc86c50788304d2c82fd66459225b7"}, {"name": "2018-11-12_Clipping_Jugs_-_Super_Bunny_Man_8_[29332].jpg", "filesize": 188866, "file_ext": "jpg", "md5": "2c1070c97c6cb848375dabee06ce9c08"}, {"name": "2018-11-12_Clipping_Jugs_-_Super_Bunny_Man_8_[29332].mp4", "filesize": 1150335419, "file_ext": "mp4", "md5": "7eec8437eaf37914c78610c9cfc3c35e"}]}}, {"id": 29438, "type": "episode", "attributes": {"title": "Oxygen is Getting Low - Super Bunny Man (#9)", "slug": "play-pals-2018-bunny-man-9", "rating": null, "caption": "In order for the Play Pals to beat Super Bunny Man, they'll have to overcome a lot of water and a ton of spike traps.", "number": 17, "description": "In order for the Play Pals to beat Super Bunny Man, they'll have to overcome a lot of water and a ton of spike traps.\r\nThe most important thing to remember when stuck underwater is not to panic. Michael and Gavin will certainly forget that every time they're stuck underwater this video.", "display_title": "Oxygen is Getting Low - Super Bunny Man (#9)", "length": 2447, "advert_config": "", "advertising": true, "ad_timestamps": "506.21,896.15,1181.40,1636.44,2145.45", "public_golive_at": "2018-11-20T18:00:00.000Z", "sponsor_golive_at": "2018-11-19T18:00:00.000Z", "member_golive_at": "2018-11-20T18:00:00.000Z", "original_air_date": "2018-11-19T18:00:00.000Z", "channel_id": "2cb2a70c-be50-46f5-93d7-84a1baabb4f7", "channel_slug": "achievement-hunter", "season_id": "9ecec38a-8210-4f38-a4c1-5601990ab8b6", "season_slug": "play-pals-2018", "season_number": 5, "show_title": "Play Pals", "show_id": "ff92a6d1-464d-11e7-a302-065410f210c4", "show_slug": "play-pals", "is_sponsors_only": false, "member_tier_i": -1, "sort_number": 50017, "genres": ["Gaming"], "is_live": true, "is_schedulable": true, "season_order": "desc", "episode_order": "desc", "downloadable": true, "blacklisted_countries": [], "upsell_next": false, "trending_score": 1.0, "time_boost": 18.111918, "credits_start_at": null, "trending_carousel": null}, "uuid": "0f5afa7f-60be-49da-bdde-4a09eb0fb54f", "canonical_links": {"self": "/watch/play-pals-2018-bunny-man-9", "show": "/series/play-pals"}, "archive": {"id": "roosterteeth-29438", "status": "archived", "files": [{"name": "2018-11-19_Oxygen_is_Getting_Low_-_Super_Bunny_Man_9_[29438].description", "filesize": 287, "file_ext": "description", "md5": "e90ecfab41cf2cafa2c71e66435975e1"}, {"name": "2018-11-19_Oxygen_is_Getting_Low_-_Super_Bunny_Man_9_[29438].info.json", "filesize": 19926, "file_ext": "json", "md5": "6d894aa2b19585faf47ddf2fd2693635"}, {"name": "2018-11-19_Oxygen_is_Getting_Low_-_Super_Bunny_Man_9_[29438].jpg", "filesize": 117723, "file_ext": "jpg", "md5": "1b05f9edba40c53a4231c322e81d10d9"}, {"name": "2018-11-19_Oxygen_is_Getting_Low_-_Super_Bunny_Man_9_[29438].mp4", "filesize": 1286581188, "file_ext": "mp4", "md5": "e2e5ea8184142c8e69ccdbd9e2ad4f0d"}]}}, {"id": 29472, "type": "episode", "attributes": {"title": "Underwater Lads - Super Bunny Man (#10)", "slug": "play-pals-2018-super-bunny-man-10", "rating": null, "caption": "In an effort to finish this level, the boys jump over spikes, swim under spikes, and forget that oxygen is important!", "number": 18, "description": "In an effort to finish this level, the boys jump over spikes, swim under spikes, and forget that oxygen is important!", "display_title": "Underwater Lads - Super Bunny Man (#10)", "length": 1664, "advert_config": "", "advertising": true, "ad_timestamps": "356.05,727.30,1109.01", "public_golive_at": "2018-11-21T18:00:00.000Z", "sponsor_golive_at": "2018-11-20T18:00:00.000Z", "member_golive_at": "2018-11-21T18:00:00.000Z", "original_air_date": "2018-11-20T18:00:00.000Z", "channel_id": "2cb2a70c-be50-46f5-93d7-84a1baabb4f7", "channel_slug": "achievement-hunter", "season_id": "9ecec38a-8210-4f38-a4c1-5601990ab8b6", "season_slug": "play-pals-2018", "season_number": 5, "show_title": "Play Pals", "show_id": "ff92a6d1-464d-11e7-a302-065410f210c4", "show_slug": "play-pals", "is_sponsors_only": false, "member_tier_i": -1, "sort_number": 50018, "genres": ["Gaming"], "is_live": true, "is_schedulable": true, "season_order": "desc", "episode_order": "desc", "downloadable": true, "blacklisted_countries": [], "upsell_next": false, "trending_score": 1.0, "time_boost": 18.112018, "credits_start_at": null, "trending_carousel": null}, "uuid": "ba7fd8c8-db9b-4d60-8dea-5712934875db", "canonical_links": {"self": "/watch/play-pals-2018-super-bunny-man-10", "show": "/series/play-pals"}, "archive": {"id": "roosterteeth-29472", "status": "archived", "files": [{"name": "2018-11-20_Underwater_Lads_-_Super_Bunny_Man_10_[29472].description", "filesize": 117, "file_ext": "description", "md5": "232f97d08fc400f14bceff112996f146"}, {"name": "2018-11-20_Underwater_Lads_-_Super_Bunny_Man_10_[29472].info.json", "filesize": 19694, "file_ext": "json", "md5": "42202245e083745c7c4007b24f2855bd"}, {"name": "2018-11-20_Underwater_Lads_-_Super_Bunny_Man_10_[29472].jpg", "filesize": 182004, "file_ext": "jpg", "md5": "dd7ed7dd81a873bac23c194431b3f398"}, {"name": "2018-11-20_Underwater_Lads_-_Super_Bunny_Man_10_[29472].mp4", "filesize": 874566088, "file_ext": "mp4", "md5": "9f73221bf410be667594c6d8513640c0"}]}}, {"id": 29511, "type": "episode", "attributes": {"title": "Nickin' Necks - Super Bunny Man (#11)", "slug": "play-pals-2018-super-bunny-man-11", "rating": null, "caption": "Join the Play Pals in another easy day of climbing, swimming, and diving on the Super Bunny Beach. It's easy and fun!", "number": 19, "description": "Join the Play Pals in another easy day of climbing, swimming, and diving on the Super Bunny Beach. It's easy and fun!", "display_title": "Nickin' Necks - Super Bunny Man (#11)", "length": 2370, "advert_config": "", "advertising": true, "ad_timestamps": "481.56,972.05,1464.23,1893.55", "public_golive_at": "2018-11-22T18:00:00.000Z", "sponsor_golive_at": "2018-11-21T18:00:00.000Z", "member_golive_at": "2018-11-22T18:00:00.000Z", "original_air_date": "2018-11-21T18:00:00.000Z", "channel_id": "2cb2a70c-be50-46f5-93d7-84a1baabb4f7", "channel_slug": "achievement-hunter", "season_id": "9ecec38a-8210-4f38-a4c1-5601990ab8b6", "season_slug": "play-pals-2018", "season_number": 5, "show_title": "Play Pals", "show_id": "ff92a6d1-464d-11e7-a302-065410f210c4", "show_slug": "play-pals", "is_sponsors_only": false, "member_tier_i": -1, "sort_number": 50019, "genres": ["Gaming"], "is_live": true, "is_schedulable": true, "season_order": "desc", "episode_order": "desc", "downloadable": true, "blacklisted_countries": [], "upsell_next": false, "trending_score": 1.0, "time_boost": 18.112118, "credits_start_at": null, "trending_carousel": null}, "uuid": "c0412938-017f-44c3-87d8-ebf725e14632", "canonical_links": {"self": "/watch/play-pals-2018-super-bunny-man-11", "show": "/series/play-pals"}, "archive": {"id": "roosterteeth-29511", "status": "archived", "files": [{"name": "2018-11-21_Nickin_Necks_-_Super_Bunny_Man_11_[29511].description", "filesize": 117, "file_ext": "description", "md5": "6216e6ff2d04f4742c75b1a636a98833"}, {"name": "2018-11-21_Nickin_Necks_-_Super_Bunny_Man_11_[29511].info.json", "filesize": 19689, "file_ext": "json", "md5": "80d90eefc8ee516232384041b3d85fd1"}, {"name": "2018-11-21_Nickin_Necks_-_Super_Bunny_Man_11_[29511].jpg", "filesize": 182895, "file_ext": "jpg", "md5": "8d8869ffceacfa64ec3264a4e17d527e"}, {"name": "2018-11-21_Nickin_Necks_-_Super_Bunny_Man_11_[29511].mp4", "filesize": 1246999795, "file_ext": "mp4", "md5": "cc5dc5373a87fc1af520b7efe12f240e"}]}}, {"id": 29515, "type": "episode", "attributes": {"title": "Return of the Summer Bois - Super Bunny Man (#12)", "slug": "play-pals-2018-super-bunny-man-12", "rating": null, "caption": "Summer is back for the boys in this action-packed Jet-ski-filled totally not hard level of Super Bunny Man!", "number": 20, "description": "Summer is back for the boys in this action-packed Jet-ski-filled totally not hard level of Super Bunny Man!", "display_title": "Return of the Summer Bois - Super Bunny Man (#12)", "length": 1669, "advert_config": "", "advertising": true, "ad_timestamps": "495.49,1049.50,1468.37", "public_golive_at": "2018-11-23T18:00:00.000Z", "sponsor_golive_at": "2018-11-22T18:00:00.000Z", "member_golive_at": "2018-11-23T18:00:00.000Z", "original_air_date": "2018-11-22T18:00:00.000Z", "channel_id": "2cb2a70c-be50-46f5-93d7-84a1baabb4f7", "channel_slug": "achievement-hunter", "season_id": "9ecec38a-8210-4f38-a4c1-5601990ab8b6", "season_slug": "play-pals-2018", "season_number": 5, "show_title": "Play Pals", "show_id": "ff92a6d1-464d-11e7-a302-065410f210c4", "show_slug": "play-pals", "is_sponsors_only": false, "member_tier_i": -1, "sort_number": 50020, "genres": ["Gaming"], "is_live": true, "is_schedulable": true, "season_order": "desc", "episode_order": "desc", "downloadable": true, "blacklisted_countries": [], "upsell_next": false, "trending_score": 1.0, "time_boost": 18.112218, "credits_start_at": null, "trending_carousel": null}, "uuid": "5d899419-cb17-4e8f-a47c-a8c5d029fa80", "canonical_links": {"self": "/watch/play-pals-2018-super-bunny-man-12", "show": "/series/play-pals"}, "archive": {"id": "roosterteeth-29515", "status": "archived", "files": [{"name": "2018-11-22_Return_of_the_Summer_Bois_-_Super_Bunny_Man_12_[29515].description", "filesize": 107, "file_ext": "description", "md5": "cd79c3533d7a28d0b0de82913ad0a611"}, {"name": "2018-11-22_Return_of_the_Summer_Bois_-_Super_Bunny_Man_12_[29515].info.json", "filesize": 19726, "file_ext": "json", "md5": "82201c7902fa557f53346262d82a254f"}, {"name": "2018-11-22_Return_of_the_Summer_Bois_-_Super_Bunny_Man_12_[29515].jpg", "filesize": 193283, "file_ext": "jpg", "md5": "94cc5827e7ab6fd457777428ef92c411"}, {"name": "2018-11-22_Return_of_the_Summer_Bois_-_Super_Bunny_Man_12_[29515].mp4", "filesize": 874149920, "file_ext": "mp4", "md5": "fc1f3fadfa2abc8f4e1af2adb4f3eaed"}]}}, {"id": 29514, "type": "episode", "attributes": {"title": "The Final Level - Super Bunny Man (#13)", "slug": "play-pals-2018-super-bunny-man-13", "rating": null, "caption": "The Play Pals have reached the final level of Super Bunny Man. But can they beat it? Or will they have to put on those costumes again?", "number": 21, "description": "The Play Pals have reached the final level of Super Bunny Man. But can they beat it? Or will they have to put on those costumes again?", "display_title": "The Final Level - Super Bunny Man (#13)", "length": 1916, "advert_config": "", "advertising": true, "ad_timestamps": "360.35,722.50,1085.38,1448.17", "public_golive_at": "2018-11-24T18:00:00.000Z", "sponsor_golive_at": "2018-11-23T18:00:00.000Z", "member_golive_at": "2018-11-24T18:00:00.000Z", "original_air_date": "2018-11-23T18:00:00.000Z", "channel_id": "2cb2a70c-be50-46f5-93d7-84a1baabb4f7", "channel_slug": "achievement-hunter", "season_id": "9ecec38a-8210-4f38-a4c1-5601990ab8b6", "season_slug": "play-pals-2018", "season_number": 5, "show_title": "Play Pals", "show_id": "ff92a6d1-464d-11e7-a302-065410f210c4", "show_slug": "play-pals", "is_sponsors_only": false, "member_tier_i": -1, "sort_number": 50021, "genres": ["Gaming"], "is_live": true, "is_schedulable": true, "season_order": "desc", "episode_order": "desc", "downloadable": true, "blacklisted_countries": [], "upsell_next": false, "trending_score": 1.0, "time_boost": 18.112318, "credits_start_at": null, "trending_carousel": null}, "uuid": "eb1f4eea-628b-491b-9240-a62fb9fe5a62", "canonical_links": {"self": "/watch/play-pals-2018-super-bunny-man-13", "show": "/series/play-pals"}, "archive": {"id": "roosterteeth-29514", "status": "archived", "files": [{"name": "2018-11-23_The_Final_Level_-_Super_Bunny_Man_13_[29514].description", "filesize": 134, "file_ext": "description", "md5": "8b89df97a441c16042f4bf0c01fe2a2a"}, {"name": "2018-11-23_The_Final_Level_-_Super_Bunny_Man_13_[29514].info.json", "filesize": 19837, "file_ext": "json", "md5": "7fc561777dc1d3670e638b5f218334ac"}, {"name": "2018-11-23_The_Final_Level_-_Super_Bunny_Man_13_[29514].jpg", "filesize": 177981, "file_ext": "jpg", "md5": "33bc5d4d1881ac1dbf8bd359d6c7b8a0"}, {"name": "2018-11-23_The_Final_Level_-_Super_Bunny_Man_13_[29514].mp4", "filesize": 1005277984, "file_ext": "mp4", "md5": "9ad671367840438482f102a4260b0e4f"}]}}, {"id": 29656, "type": "episode", "attributes": {"title": "The Lost Level - Super Bunny Man (#14)", "slug": "play-pals-2018-the-lost-level-super-bunny-man-14", "rating": null, "caption": "After losing footage in part 10, the Bunny Pals go back to re-film level 37. But now that it's an enitely new level, we've got a whole bonus part 14 (or part 10.5?), the lost level of Super Bunny Man.", "number": 22, "description": "After losing footage in part 10, the Bunny Pals go back to re-film level 37. But now that it's an enitely new level, we've got a whole bonus part 14 (or part 10.5?), the lost level of Super Bunny Man.", "display_title": "The Lost Level - Super Bunny Man (#14)", "length": 2394, "advert_config": "", "advertising": true, "ad_timestamps": "429.29,909.27,1450.49,1900.18", "public_golive_at": "2018-12-04T18:00:00.000Z", "sponsor_golive_at": "2018-12-03T18:00:00.000Z", "member_golive_at": "2018-12-04T18:00:00.000Z", "original_air_date": "2018-12-03T18:00:00.000Z", "channel_id": "2cb2a70c-be50-46f5-93d7-84a1baabb4f7", "channel_slug": "achievement-hunter", "season_id": "9ecec38a-8210-4f38-a4c1-5601990ab8b6", "season_slug": "play-pals-2018", "season_number": 5, "show_title": "Play Pals", "show_id": "ff92a6d1-464d-11e7-a302-065410f210c4", "show_slug": "play-pals", "is_sponsors_only": false, "member_tier_i": -1, "sort_number": 50022, "genres": ["Gaming"], "is_live": true, "is_schedulable": true, "season_order": "desc", "episode_order": "desc", "downloadable": true, "blacklisted_countries": [], "upsell_next": false, "trending_score": 1.0, "time_boost": 18.120318, "credits_start_at": null, "trending_carousel": null}, "uuid": "01f7d5ec-22cd-4f8d-addc-0ef692dd74c3", "canonical_links": {"self": "/watch/play-pals-2018-the-lost-level-super-bunny-man-14", "show": "/series/play-pals"}, "archive": {"id": "roosterteeth-29656", "status": "archived", "files": [{"name": "2018-12-03_The_Lost_Level_-_Super_Bunny_Man_14_[29656].description", "filesize": 200, "file_ext": "description", "md5": "5bc2f74541bc56561a97e1f7c552edc8"}, {"name": "2018-12-03_The_Lost_Level_-_Super_Bunny_Man_14_[29656].info.json", "filesize": 19901, "file_ext": "json", "md5": "6050aa22c682b006ebd83514570dddfe"}, {"name": "2018-12-03_The_Lost_Level_-_Super_Bunny_Man_14_[29656].jpg", "filesize": 142242, "file_ext": "jpg", "md5": "af66d82cb873b08ce5771c33e73b8b86"}, {"name": "2018-12-03_The_Lost_Level_-_Super_Bunny_Man_14_[29656].mp4", "filesize": 1261587900, "file_ext": "mp4", "md5": "8a1fc467ab79873b21695a32ee6d061b"}]}}, {"id": 30010, "type": "episode", "attributes": {"title": "EXTREME NURSERY RHYMES - Guts and Glory", "slug": "play-pals-2018-extreme-nursery-rhymes-guts-and-glory", "rating": null, "caption": "Michael and Gavin return to Guts and Glory for a bloody good time.", "number": 23, "description": "Michael and Gavin return to Guts and Glory for a bloody good time.\r\n\r\nJack and Jill went up the hill,\r\ndodging arrows with great skill.\r\nJack got hit, Jill was split,\r\nbut in the end, they would not quit.\r\n\r\nOncoming cars, led to scars,\r\nand bloody streaks along the tar.\r\nThen there's the truck.\r\nGavin's a scmuck.\r\nAnd I don't want to rhyme anymore.", "display_title": "EXTREME NURSERY RHYMES - Guts and Glory", "length": 2145, "advert_config": "", "advertising": true, "ad_timestamps": "477.48,824.27,1235.39,1622.10", "public_golive_at": "2018-12-25T18:00:00.000Z", "sponsor_golive_at": "2018-12-24T18:00:00.000Z", "member_golive_at": "2018-12-25T18:00:00.000Z", "original_air_date": "2018-12-24T18:00:00.000Z", "channel_id": "2cb2a70c-be50-46f5-93d7-84a1baabb4f7", "channel_slug": "achievement-hunter", "season_id": "9ecec38a-8210-4f38-a4c1-5601990ab8b6", "season_slug": "play-pals-2018", "season_number": 5, "show_title": "Play Pals", "show_id": "ff92a6d1-464d-11e7-a302-065410f210c4", "show_slug": "play-pals", "is_sponsors_only": false, "member_tier_i": -1, "sort_number": 50023, "genres": ["Gaming"], "is_live": true, "is_schedulable": true, "season_order": "desc", "episode_order": "desc", "downloadable": true, "blacklisted_countries": [], "upsell_next": false, "trending_score": 1.0, "time_boost": 18.122418, "credits_start_at": null, "trending_carousel": null}, "uuid": "acf5463a-1566-460f-b08d-bf04667c63d8", "canonical_links": {"self": "/watch/play-pals-2018-extreme-nursery-rhymes-guts-and-glory", "show": "/series/play-pals"}, "archive": {"id": "roosterteeth-30010", "status": "archived", "files": [{"name": "2018-12-24_EXTREME_NURSERY_RHYMES_-_Guts_and_Glory_[30010].description", "filesize": 351, "file_ext": "description", "md5": "35944403312df9aafcaa6fead20a731e"}, {"name": "2018-12-24_EXTREME_NURSERY_RHYMES_-_Guts_and_Glory_[30010].info.json", "filesize": 20019, "file_ext": "json", "md5": "45ed43e89b0a369b8f935874961032d0"}, {"name": "2018-12-24_EXTREME_NURSERY_RHYMES_-_Guts_and_Glory_[30010].mp4", "filesize": 1115490283, "file_ext": "mp4", "md5": "c58a6b10e1f7344ff7a0a99f1b75953c"}, {"name": "2018-12-24_EXTREME_NURSERY_RHYMES_-_Guts_and_Glory_[30010].png", "filesize": 159992, "file_ext": "png", "md5": "058e172cb7cb410444f766bef951aa83"}]}}, {"id": 26401, "type": "episode", "attributes": {"title": "Let's Play Pals - A Way Out (#1)", "slug": "let-s-play-2018-let-s-play-pals-a-way-out-1", "rating": null, "caption": "It's the Play Pals on Let's Play doing a Let's Play Pals in A Way Out. Co-op teamwork is essential to make it through this lockdown, so you know Gavin and Michael are hardly up for the challenge.", "number": 64, "description": "It's the Play Pals on Let's Play doing a Let's Play Pals in A Way Out. Co-op teamwork is essential to make it through this lockdown, so you know Gavin and Michael are hardly up for the challenge.", "display_title": "Let's Play Pals - A Way Out (#1)", "length": 2985, "advert_config": "", "advertising": true, "ad_timestamps": "0.00,497.50,995.00,1492.50,1990.00,2487.50", "public_golive_at": "2018-04-10T19:00:00.000Z", "sponsor_golive_at": "2018-04-09T19:00:00.000Z", "member_golive_at": "2018-04-10T19:00:00.000Z", "original_air_date": "2018-04-09T19:00:00.000Z", "channel_id": "2cb2a70c-be50-46f5-93d7-84a1baabb4f7", "channel_slug": "achievement-hunter", "season_id": "9ecec38a-8210-4f38-a4c1-5601990ab8b6", "season_slug": "play-pals-2018", "season_number": 5, "show_title": "Play Pals", "show_id": "ff92a6d1-464d-11e7-a302-065410f210c4", "show_slug": "play-pals", "is_sponsors_only": false, "member_tier_i": -1, "sort_number": 50064, "genres": ["Gaming"], "is_live": true, "is_schedulable": true, "season_order": "desc", "episode_order": "desc", "downloadable": true, "blacklisted_countries": [], "upsell_next": false, "trending_score": 1.0, "time_boost": 18.040919, "credits_start_at": null, "trending_carousel": null}, "uuid": "e08ccc32-0dd0-415b-9319-a7fc4a2ace5f", "canonical_links": {"self": "/watch/let-s-play-2018-let-s-play-pals-a-way-out-1", "show": "/series/play-pals"}, "archive": {"id": "roosterteeth-26401", "status": "archived", "files": [{"name": "2018-04-09_Lets_Play_Pals_-_A_Way_Out_1_[26401].description", "filesize": 195, "file_ext": "description", "md5": "8f31fc938bbba9a36a39171178b9d096"}, {"name": "2018-04-09_Lets_Play_Pals_-_A_Way_Out_1_[26401].info.json", "filesize": 19792, "file_ext": "json", "md5": "219aa0d1fb161112ee477248565afe22"}, {"name": "2018-04-09_Lets_Play_Pals_-_A_Way_Out_1_[26401].jpg", "filesize": 204981, "file_ext": "jpg", "md5": "fccbce1dbf44d27c7b097f8c1956ec16"}, {"name": "2018-04-09_Lets_Play_Pals_-_A_Way_Out_1_[26401].mp4", "filesize": 1565914546, "file_ext": "mp4", "md5": "b8f16ba9539afa0cfacd2d956fcde53d"}]}}, {"id": 26428, "type": "episode", "attributes": {"title": "Let's Play Pals - A Way Out \u00e2\u20ac\u201c Inside Out (#2)", "slug": "let-s-play-2018-let-s-play-pals-a-way-out-2", "rating": null, "caption": "Back from their first failed attempt at escaping, Gavin and Michael are still trying to find A Way Out of prison. Turns out a little butt to butt action might be their key.", "number": 66, "description": "Back from their first failed attempt at escaping, Gavin and Michael are still trying to find A Way Out of prison. Turns out a little butt to butt action might be their key.", "display_title": "Let's Play Pals - A Way Out \u00e2\u20ac\u201c Inside Out (#2)", "length": 3063, "advert_config": "", "advertising": true, "ad_timestamps": "0.00,510.50,1021.00,1531.50,2042.00,2552.50", "public_golive_at": "2018-04-11T19:00:00.000Z", "sponsor_golive_at": "2018-04-10T19:00:00.000Z", "member_golive_at": "2018-04-11T19:00:00.000Z", "original_air_date": "2018-04-10T19:00:00.000Z", "channel_id": "2cb2a70c-be50-46f5-93d7-84a1baabb4f7", "channel_slug": "achievement-hunter", "season_id": "9ecec38a-8210-4f38-a4c1-5601990ab8b6", "season_slug": "play-pals-2018", "season_number": 5, "show_title": "Play Pals", "show_id": "ff92a6d1-464d-11e7-a302-065410f210c4", "show_slug": "play-pals", "is_sponsors_only": false, "member_tier_i": -1, "sort_number": 50066, "genres": ["Gaming"], "is_live": true, "is_schedulable": true, "season_order": "desc", "episode_order": "desc", "downloadable": true, "blacklisted_countries": [], "upsell_next": false, "trending_score": 1.0, "time_boost": 18.041019, "credits_start_at": null, "trending_carousel": null}, "uuid": "14c0294f-72e1-46b2-9130-ad5b33754484", "canonical_links": {"self": "/watch/let-s-play-2018-let-s-play-pals-a-way-out-2", "show": "/series/play-pals"}, "archive": {"id": "roosterteeth-26428", "status": "archived", "files": [{"name": "2018-04-10_Lets_Play_Pals_-_A_Way_Out_\u00e2_Inside_Out_2_[26428].description", "filesize": 172, "file_ext": "description", "md5": "194ebf04b9c7b34befa9e6c1173883a1"}, {"name": "2018-04-10_Lets_Play_Pals_-_A_Way_Out_\u00e2_Inside_Out_2_[26428].info.json", "filesize": 19799, "file_ext": "json", "md5": "7ce776db76fa0295cb5732591648a812"}, {"name": "2018-04-10_Lets_Play_Pals_-_A_Way_Out_\u00e2_Inside_Out_2_[26428].jpg", "filesize": 229528, "file_ext": "jpg", "md5": "906fd323e82e7f34dddeb3087c950b8e"}, {"name": "2018-04-10_Lets_Play_Pals_-_A_Way_Out_\u00e2_Inside_Out_2_[26428].mp4", "filesize": 1606789576, "file_ext": "mp4", "md5": "cb2ad20ae0f50ca061d6ad1c93ff2eac"}]}}, {"id": 26446, "type": "episode", "attributes": {"title": "Let's Play Pals - A Way Out - Fists Blazing (#3)", "slug": "let-s-play-2018-let-s-play-pals-a-way-out-fists-blazing-3", "rating": null, "caption": "They've escaped, but what now? They're hungry, their feet hurt, and Gavin really wants some of those old lady's cookies.", "number": 68, "description": "They've escaped, but what now? They're hungry, their feet hurt, and Gavin really wants some of those old lady's cookies.", "display_title": "Let's Play Pals - A Way Out - Fists Blazing (#3)", "length": 2815, "advert_config": "", "advertising": true, "ad_timestamps": "0.00,469.17,938.33,1407.50,1876.67,2345.83", "public_golive_at": "2018-04-12T19:00:00.000Z", "sponsor_golive_at": "2018-04-11T19:00:00.000Z", "member_golive_at": "2018-04-12T19:00:00.000Z", "original_air_date": "2018-04-11T19:00:00.000Z", "channel_id": "2cb2a70c-be50-46f5-93d7-84a1baabb4f7", "channel_slug": "achievement-hunter", "season_id": "9ecec38a-8210-4f38-a4c1-5601990ab8b6", "season_slug": "play-pals-2018", "season_number": 5, "show_title": "Play Pals", "show_id": "ff92a6d1-464d-11e7-a302-065410f210c4", "show_slug": "play-pals", "is_sponsors_only": false, "member_tier_i": -1, "sort_number": 50068, "genres": ["Gaming"], "is_live": true, "is_schedulable": true, "season_order": "desc", "episode_order": "desc", "downloadable": true, "blacklisted_countries": [], "upsell_next": false, "trending_score": 1.0, "time_boost": 18.041119, "credits_start_at": null, "trending_carousel": null}, "uuid": "31dc8210-c74b-4b43-b155-3ffd639aa58c", "canonical_links": {"self": "/watch/let-s-play-2018-let-s-play-pals-a-way-out-fists-blazing-3", "show": "/series/play-pals"}, "archive": {"id": "roosterteeth-26446", "status": "archived", "files": [{"name": "2018-04-11_Lets_Play_Pals_-_A_Way_Out_-_Fists_Blazing_3_[26446].description", "filesize": 120, "file_ext": "description", "md5": "79f53333a7d4469b7c99be4ef9392577"}, {"name": "2018-04-11_Lets_Play_Pals_-_A_Way_Out_-_Fists_Blazing_3_[26446].info.json", "filesize": 19843, "file_ext": "json", "md5": "2862898497657fabf109a3a760cd1d33"}, {"name": "2018-04-11_Lets_Play_Pals_-_A_Way_Out_-_Fists_Blazing_3_[26446].jpg", "filesize": 212896, "file_ext": "jpg", "md5": "4d29ca370390b7d9c4e7765fa559b351"}, {"name": "2018-04-11_Lets_Play_Pals_-_A_Way_Out_-_Fists_Blazing_3_[26446].mp4", "filesize": 1480205358, "file_ext": "mp4", "md5": "c2cd4bed74648841b928c30a801304c4"}]}}, {"id": 26451, "type": "episode", "attributes": {"title": "Let's Play Pals - A Way Out - Farting Around (#4)", "slug": "let-s-play-2018-let-s-play-pals-a-way-out-farting-around-4", "rating": null, "caption": "Michael and Gavin eluded the authorities for the moment, but now they've got to find Harvey for revenge-time.", "number": 70, "description": "Michael and Gavin eluded the authorities for the moment, but now they've got to find Harvey for revenge-time. Unfortunately, they may get distracted by a dart game or two, some arm wrestling, or even a porta potty. They'll catch the bad guys, eventually.", "display_title": "Let's Play Pals - A Way Out - Farting Around (#4)", "length": 3175, "advert_config": "", "advertising": true, "ad_timestamps": "0.00,529.17,1058.33,1587.50,2116.67,2645.83", "public_golive_at": "2018-04-13T19:00:00.000Z", "sponsor_golive_at": "2018-04-12T19:00:00.000Z", "member_golive_at": "2018-04-13T19:00:00.000Z", "original_air_date": "2018-04-12T19:00:00.000Z", "channel_id": "2cb2a70c-be50-46f5-93d7-84a1baabb4f7", "channel_slug": "achievement-hunter", "season_id": "9ecec38a-8210-4f38-a4c1-5601990ab8b6", "season_slug": "play-pals-2018", "season_number": 5, "show_title": "Play Pals", "show_id": "ff92a6d1-464d-11e7-a302-065410f210c4", "show_slug": "play-pals", "is_sponsors_only": false, "member_tier_i": -1, "sort_number": 50070, "genres": ["Gaming"], "is_live": true, "is_schedulable": true, "season_order": "desc", "episode_order": "desc", "downloadable": true, "blacklisted_countries": [], "upsell_next": false, "trending_score": 1.0, "time_boost": 18.041219, "credits_start_at": null, "trending_carousel": null}, "uuid": "2f26497e-0ce8-471a-b329-2cdf5f0eb617", "canonical_links": {"self": "/watch/let-s-play-2018-let-s-play-pals-a-way-out-farting-around-4", "show": "/series/play-pals"}, "archive": {"id": "roosterteeth-26451", "status": "archived", "files": [{"name": "2018-04-12_Lets_Play_Pals_-_A_Way_Out_-_Farting_Around_4_[26451].description", "filesize": 254, "file_ext": "description", "md5": "13e899cc8997782285c0885e30f5eae9"}, {"name": "2018-04-12_Lets_Play_Pals_-_A_Way_Out_-_Farting_Around_4_[26451].info.json", "filesize": 19942, "file_ext": "json", "md5": "2f6856e3a70dafadce48070af4be682b"}, {"name": "2018-04-12_Lets_Play_Pals_-_A_Way_Out_-_Farting_Around_4_[26451].jpg", "filesize": 160764, "file_ext": "jpg", "md5": "2570d6e9df0d6bbf18458960af3bd7ab"}, {"name": "2018-04-12_Lets_Play_Pals_-_A_Way_Out_-_Farting_Around_4_[26451].mp4", "filesize": 1657380460, "file_ext": "mp4", "md5": "4371715a8a88eb0690a65bc4870633ef"}]}}, {"id": 26464, "type": "episode", "attributes": {"title": "Play Pals - A Way Out - Makin' a Baby  (#5)", "slug": "let-s-play-2018-play-pals-a-way-out-makin-a-baby-5", "rating": null, "caption": "With the prison far away from them, Michael and Gavin become even closer together as friends as they get baby crazy while trying to find A Way Out of new buildings, like theaters and hospitals.", "number": 71, "description": "With the prison far away from them, Michael and Gavin become even closer together as friends as they get baby crazy while trying to find A Way Out of new buildings, like theaters and hospitals.", "display_title": "Play Pals - A Way Out - Makin' a Baby  (#5)", "length": 3468, "advert_config": "", "advertising": true, "ad_timestamps": "0.00,495.43,990.86,1486.29,1981.71,2477.14,2972.57", "public_golive_at": "2018-04-14T19:00:00.000Z", "sponsor_golive_at": "2018-04-13T19:00:00.000Z", "member_golive_at": "2018-04-14T19:00:00.000Z", "original_air_date": "2018-04-13T19:00:00.000Z", "channel_id": "2cb2a70c-be50-46f5-93d7-84a1baabb4f7", "channel_slug": "achievement-hunter", "season_id": "9ecec38a-8210-4f38-a4c1-5601990ab8b6", "season_slug": "play-pals-2018", "season_number": 5, "show_title": "Play Pals", "show_id": "ff92a6d1-464d-11e7-a302-065410f210c4", "show_slug": "play-pals", "is_sponsors_only": false, "member_tier_i": -1, "sort_number": 50071, "genres": ["Gaming"], "is_live": true, "is_schedulable": true, "season_order": "desc", "episode_order": "desc", "downloadable": true, "blacklisted_countries": [], "upsell_next": false, "trending_score": 1.0, "time_boost": 18.041319, "credits_start_at": null, "trending_carousel": null}, "uuid": "1b4db0b3-9358-45a3-b7aa-a2f1be9ffd62", "canonical_links": {"self": "/watch/let-s-play-2018-play-pals-a-way-out-makin-a-baby-5", "show": "/series/play-pals"}, "archive": {"id": "roosterteeth-26464", "status": "archived", "files": [{"name": "2018-04-13_Play_Pals_-_A_Way_Out_-_Makin_a_Baby__5_[26464].description", "filesize": 193, "file_ext": "description", "md5": "71ff85c9cf4fb8893c7f72a8177649fa"}, {"name": "2018-04-13_Play_Pals_-_A_Way_Out_-_Makin_a_Baby__5_[26464].info.json", "filesize": 19839, "file_ext": "json", "md5": "5c2d27de9cfd35a688cdb79273f99c72"}, {"name": "2018-04-13_Play_Pals_-_A_Way_Out_-_Makin_a_Baby__5_[26464].jpg", "filesize": 169944, "file_ext": "jpg", "md5": "6aef116215e762da76b26fd356063bc5"}, {"name": "2018-04-13_Play_Pals_-_A_Way_Out_-_Makin_a_Baby__5_[26464].mp4", "filesize": 1818104048, "file_ext": "mp4", "md5": "a5d01b9d5a3cc6a7ae4fe7fde9b6caa4"}]}}, {"id": 26495, "type": "episode", "attributes": {"title": "Let's Play Pals - A Way Out - Pumping Iron (#6)", "slug": "let-s-play-2018-let-s-play-pals-a-way-out-pumping-iron-6", "rating": null, "caption": "Michael and Gavin are makin their way to Mexico to shoot some bad guys, but first they got to pump some sweet sweet iron.", "number": 75, "description": "Michael and Gavin are makin their way to Mexico to shoot some bad guys, but first they got to pump some sweet sweet iron.", "display_title": "Let's Play Pals - A Way Out - Pumping Iron (#6)", "length": 2940, "advert_config": "", "advertising": true, "ad_timestamps": "0.00,490.00,980.00,1470.00,1960.00,2450.00", "public_golive_at": "2018-04-15T19:00:00.000Z", "sponsor_golive_at": "2018-04-14T19:00:00.000Z", "member_golive_at": "2018-04-15T19:00:00.000Z", "original_air_date": "2018-04-14T19:00:00.000Z", "channel_id": "2cb2a70c-be50-46f5-93d7-84a1baabb4f7", "channel_slug": "achievement-hunter", "season_id": "9ecec38a-8210-4f38-a4c1-5601990ab8b6", "season_slug": "play-pals-2018", "season_number": 5, "show_title": "Play Pals", "show_id": "ff92a6d1-464d-11e7-a302-065410f210c4", "show_slug": "play-pals", "is_sponsors_only": false, "member_tier_i": -1, "sort_number": 50075, "genres": ["Gaming"], "is_live": true, "is_schedulable": true, "season_order": "desc", "episode_order": "desc", "downloadable": true, "blacklisted_countries": [], "upsell_next": false, "trending_score": 1.0, "time_boost": 18.041419, "credits_start_at": null, "trending_carousel": null}, "uuid": "87560646-e961-4d96-b3a1-da05999652ab", "canonical_links": {"self": "/watch/let-s-play-2018-let-s-play-pals-a-way-out-pumping-iron-6", "show": "/series/play-pals"}, "archive": {"id": "roosterteeth-26495", "status": "archived", "files": [{"name": "2018-04-14_Lets_Play_Pals_-_A_Way_Out_-_Pumping_Iron_6_[26495].description", "filesize": 121, "file_ext": "description", "md5": "46dfdd58f37cbb950dfb4b30d7f5ec09"}, {"name": "2018-04-14_Lets_Play_Pals_-_A_Way_Out_-_Pumping_Iron_6_[26495].info.json", "filesize": 19797, "file_ext": "json", "md5": "31bcf0cdc3987ac8dc241fea35589fd2"}, {"name": "2018-04-14_Lets_Play_Pals_-_A_Way_Out_-_Pumping_Iron_6_[26495].jpg", "filesize": 209196, "file_ext": "jpg", "md5": "c8259e9d00203057a31359f8a27e2c33"}, {"name": "2018-04-14_Lets_Play_Pals_-_A_Way_Out_-_Pumping_Iron_6_[26495].mp4", "filesize": 1552620061, "file_ext": "mp4", "md5": "36d2ffd1f3993da998e79c65bce50dd9"}]}}, {"id": 26500, "type": "episode", "attributes": {"title": "Let's Play Pals - A Way Out - It Doesn't Have To Be Like This (End)", "slug": "let-s-play-2018-let-s-play-pals-a-way-out-it-doesn-t-have-to-be-this-way-7", "rating": null, "caption": "End of the line for our boys. Was the real way out the friends we made along the way?", "number": 78, "description": "End of the line for our boys. Was the real way out the friends we made along the way?", "display_title": "Let's Play Pals - A Way Out - It Doesn't Have To Be Like This (End)", "length": 2966, "advert_config": "", "advertising": true, "ad_timestamps": "0.00,494.33,988.67,1483.00,1977.33,2471.67", "public_golive_at": "2018-04-16T19:00:00.000Z", "sponsor_golive_at": "2018-04-15T19:00:00.000Z", "member_golive_at": "2018-04-16T19:00:00.000Z", "original_air_date": "2018-04-15T19:00:00.000Z", "channel_id": "2cb2a70c-be50-46f5-93d7-84a1baabb4f7", "channel_slug": "achievement-hunter", "season_id": "9ecec38a-8210-4f38-a4c1-5601990ab8b6", "season_slug": "play-pals-2018", "season_number": 5, "show_title": "Play Pals", "show_id": "ff92a6d1-464d-11e7-a302-065410f210c4", "show_slug": "play-pals", "is_sponsors_only": false, "member_tier_i": -1, "sort_number": 50078, "genres": ["Gaming"], "is_live": true, "is_schedulable": true, "season_order": "desc", "episode_order": "desc", "downloadable": true, "blacklisted_countries": [], "upsell_next": false, "trending_score": 1.0, "time_boost": 18.041519, "credits_start_at": null, "trending_carousel": null}, "uuid": "a6f97292-820f-4784-b142-96289cb08727", "canonical_links": {"self": "/watch/let-s-play-2018-let-s-play-pals-a-way-out-it-doesn-t-have-to-be-this-way-7", "show": "/series/play-pals"}, "archive": {"id": "roosterteeth-26500", "status": "archived", "files": [{"name": "2018-04-15_Lets_Play_Pals_-_A_Way_Out_-_It_Doesnt_Have_To_Be_Like_This_End_[26500].description", "filesize": 85, "file_ext": "description", "md5": "f138efb9b70bc3edbaabb456faae9e22"}, {"name": "2018-04-15_Lets_Play_Pals_-_A_Way_Out_-_It_Doesnt_Have_To_Be_Like_This_End_[26500].info.json", "filesize": 19885, "file_ext": "json", "md5": "8be9135384d8e44e39f4bec3062d3855"}, {"name": "2018-04-15_Lets_Play_Pals_-_A_Way_Out_-_It_Doesnt_Have_To_Be_Like_This_End_[26500].jpg", "filesize": 176537, "file_ext": "jpg", "md5": "b41a68844ef219737ca68b1f51ffb568"}, {"name": "2018-04-15_Lets_Play_Pals_-_A_Way_Out_-_It_Doesnt_Have_To_Be_Like_This_End_[26500].mp4", "filesize": 1556230357, "file_ext": "mp4", "md5": "5c07658906ec95448a951ef93b069fee"}]}}], "page": 1, "per_page": 999, "total_pages": 1, "total_results": 30}